Workbook
Name _0raw: Sheet1!$FO$5262:$FP$5269
Name _0raw_1: Sheet1!$FP$5262:$FR$5269
Name _0raw_2: Sheet1!$FP$5270:$FR$5277
Name _0raw_3: Sheet1!$FO$5270:$FP$5277
Name _0raw_5: Sheet1!$FP$5286:$FR$5293
Name _0raw_6: Sheet1!$FP$5278:$FR$5285
Name _0raw_7: Sheet1!$FO$5278:$FP$5285
Name _0raw_8: Sheet1!$FJ$5262:$FK$5269

Sheet Sheet1
A1: no | B1: Data source | C1: StudyID | D1: ExperimentID | E1: Author_F | G1: Author_G | H1: YearPublication | I1: SamplingYear | J1: Journal | K1: SiteInfor | L1: Country | M1: Latitude | N1: Longitude | O1: Elevation | P1: Tannual | Q1: MAT | R1: Pannual | S1: MAP | T1: ClimateType | U1: TimeAfterCoverCrop | V1: Duration | W1: CC_planting_date | X1: CC_termination_date | Y1: Time_Comments | Z1: SamplingDepth | AA1: SamplingThickness | AB1: CEC | AC1: CEC_Unit | AD1: SoilBD | AE1: SandPerc | AF1: SiltPerc | AG1: ClayPerc | AH1: Texture | AI1: SoilpH | AJ1: BackgroundSOC | AK1: SOC_NaturalVeg | AL1: SoilKsat | AM1: SoilFamily | AN1: CoverCrop | AO1: soil_cover | AP1: Cover crop before sowing | AQ1: CoverCropGroup | AR1: GrainCrop | AS1: GrainCropGroup | AT1: Rotation_C | AU1: rotation | AV1: Crop rotation with at least 3 crops involved | AW1: Rotation_T | AX1: Crop rotation with at least 3 crops involved | AY1: Rotation_Diff | AZ1: Tillage_C | BA1: Tillage_T | BB1: Tillage_Top_C | BC1: Tillage_Top_T | BD1: Tillage_Diff | BE1: Fertilization_C | BF1: N input | BG1: Fertilization CT | BH1: Fertilization_T | BI1: Fertilization NT | BJ1: Fert_Diff | BK1: Conservation_Type | BL1: Conservation_Discription | BM1: ControlDescription | BN1: No_C | BO1: No_T | BP1: NoSubsample | BQ1: ExperimentDesign | BR1: CCFreshBiomass | BS1: CCDryBiomass | BT1: CNOfCoverCrop | BU1: CCTermination | BV1: Others | BW1: BiomassCash_C | BX1: BiomassCash_T | BY1: BiomCash_C_SD | BZ1: BiomCash_T_SD | CA1: 1.BiomassCash_Comments | CB1: Yield_C | CC1: Yield_T | CD1: effect | CE1: Yield_C_SD | CF1: Yield_T_SD | CG1: 2.Yield_Comments | CH1: BD_C | CI1: BD_T | CJ1: BD_C_SD | CK1: BD_T_SD | CL1: 3.BD_Comments | CM1: OC_C | CN1: OC_T | CO1: OC_C_SD% | CP1: OC_T_SD% | CQ1: 4.OC_Comments | CR1: OC_Con_C | CS1: OC_Con_T | CT1: OC_C_SD | CU1: OC_T_SD | CV1: 4.2OC_Comments | CW1: OC_C_Seq | CX1: OC_T_Seq | CY1: OC_C_SD_Seq | CZ1: OC_T_SD_Seq | DA1: 4.3OC_Seq_Comments | DB1: N_C | DC1: N_T | DD1: N_C_SD | DE1: N_T_SD | DF1: 5.N_Comments | DG1: P_C | DH1: P_T | DI1: P_C_SD | DJ1: P_T_SD | DK1: 6.P_Comments | DL1: K_C | DM1: K_T | DN1: K_C_SD | DO1: K_T_SD | DP1: X7.K_Comments | DQ1: pH_C | DR1: pH_T | DS1: pH_C_SD | DT1: pH_T_SD | DU1: X8.pH_Comments | DV1: CEC_C | DW1: CEC_T | DX1: CEC_C_SD | DY1: CEC_T_SD | DZ1: X9.CEC_Comments | EA1: EC_C | EB1: EC_T | EC1: EC_C_SD | ED1: EC_T_SD | EE1: X10.EC_Comments | EF1: BS_C | EG1: BS_T | EH1: BS_C_SD | EI1: BS_T_SD | EJ1: X11.BS_Comments | EK1: Aggre_C | EL1: Aggre_T | EM1: Aggre_C_SD | EN1: Aggre_T_SD | EO1: X12.Aggre_Comments | EP1: Porosity_C | EQ1: Porosity_T | ER1: Porosity_C_SD | ES1: Porosity_T_SD | ET1: X13.Porosity_Comments | EU1: Penetration_C | EV1: Penetration_T | EW1: Penetration_C_SD | EX1: Penetration_T_SD | EY1: 14.Penetration_Comments | EZ1: Infiltration_C | FA1: Infiltration_T | FB1: Infiltration_C_SD | FC1: Infiltration_T_SD | FD1: 15.Infiltration_Comments | FE1: Ksat_C | FF1: Ksat_T | FG1: Ksat_C_SD | FH1: Ksat_T_SD | FI1: 16.Ksat_Comments | FJ1: Erosion_C | FK1: Erosion_T | FL1: Erosion_C_SD | FM1: Erosion_T_SD | FN1: 17.Erosion_Comments | FO1: Runoff_C | FP1: Runoff_T | FQ1: Runoff_C_SD | FR1: Runoff_T_SD | FS1: 18.Runoff_Comments | FT1: Leaching_C | FU1: Leaching_T | FV1: Leaching_C_SD | FW1: Leaching_T_SD | FX1: 19.Leaching_Comments | FY1: ST_C | FZ1: ST_T | GA1: ST_C_SD | GB1: ST_T_SD | GC1: 20.ST_Comments | GD1: SWC_C | GE1: SWC_T | GF1: SWC_C_SD | GG1: SWC_T_SD | GH1: 21.SWC_Comments | GI1: AWHC_C | GJ1: AWHC_T | GK1: AWHC_C_SD | GL1: AWHC_T_SD | GM1: 22.AWHC_Comments | GN1: Weed_C | GO1: Weed_T | GP1: weed_control | GQ1: Weed_C_SD | GR1: Weed_T_SD | GS1: 23.Weed_Comments | GT1: Diseases_C | GU1: Diseases_T | GV1: Diseases_C_SD | GW1: Diseases_T_SD | GX1: 24.Diseases_Comments | GY1: Pests_C | GZ1: Pests_T | HA1: Pests_C_SD | HB1: Pests_T_SD | HC1: 25.Pests_Comments | HD1: SoilFauna_C | HE1: SoilFauna_T | HF1: SoilFauna_C_SD | HG1: SoilFauna_T_SD | HH1: 26.SoilFauna_Comments | HI1: Fungal_C | HJ1: Fungal_T | HK1: Fungal_C_SD | HL1: Fungal_T_SD | HM1: 27.Fungal_Comments | HN1: OtherMicrobial_C | HO1: OtherMicrobial_T | HP1: OtherMicrobial_C_SD | HQ1: OtherMicrobial_T_SD | HR1: 28.OtherMicrobial_Comments | HS1: Enzyme_C | HT1: Enzyme_T | HU1: Enzyme_C_SD | HV1: Enzyme_T_SD | HW1: 29.Enzyme_Comments | HX1: Cmina_C | HY1: Cmina_T | HZ1: Cmina_C_SD | IA1: Cmina_T_SD | IB1: 30.Cmina_Comments | IC1: Nmina_C | ID1: Nmina_T | IE1: Nmina_C_SD | IF1: Nmina_T_SD | IG1: 31.Nmina_Comments | IH1: NxO_C | II1: NxO_T | IJ1: NxO_C_SD | IK1: NxO_T_SD | IL1: 32.NxO_Comm | IM1: SIR_C | IN1: SIR_T | IO1: SIR_C_SD | IP1: SIR_T_SD | IQ1: 33.SIR_Comments | IR1: CO2BTest_C | IS1: CO2BTest_T | IT1: CO2BTest_C_SD | IU1: CO2BTest_T_SD | IV1: 34.CO2BTest_Comments | IW1: CO2_C | IX1: CO2_T | IY1: CO2_C_SD | IZ1: CO2_T_SD | JA1: 35.CO2_Comm | JB1: CH4_C | JC1: CH4_T | JD1: CH4_C_SD | JE1: CH4_T_SD | JF1: 36.CH4_Comm | JG1: MBC_C | JH1: MBC_T | JI1: MBC_C_SD | JJ1: MBC_T_SD | JK1: 37.MBC_Comments | JL1: MBN_C | JM1: MBN_T | JN1: MBN_C_SD | JO1: MBN_T_SD | JP1: 38.MBN_Comments | JQ1: Microelement | JR1: SQI | JS1: ESS | JT1: Texture_C | JU1: Comments1 | JV1: Comments2 | JW1: Comments3
A2: 1 | B2: SoilHealthDB_V2_Jian et al | C2: 1 | D2: 1-1 | E2: Abawi | G2: G.S. | H2: 2000 | J2: Applied Soil Ecology | K2: New York | L2: USA | M2: 40.71 | N2: -74.01 | O2: 3.5 | Z2: Not-available | AA2: Not-available | AH2: NotAvailable | AN2: White_clover | AO2: yes | AQ2: Legume | AR2: Bean/Beet/Corn/Bean | AS2: MTT | AU2: Not reported | AV2: yes | AX2: yes | BK2: CC | BM2: Fallow | GP2: Not reported | GT2: 6.6 | GU2: 7 | GX2: Root diseases determined by root rot, ranged from 1(no root rot observed) to 9 (80% roots infected) | JU2: Root infected by rot
A3: 2 | B3: SoilHealthDB_V2_Jian et al | C3: 1 | D3: 1-1 | E3: Abawi | G3: G.S. | H3: 2000 | J3: Applied Soil Ecology | K3: New York | L3: USA | M3: 40.71 | N3: -74.01 | O3: 3.5 | Z3: Not-available | AA3: Not-available | AH3: NotAvailable | AN3: Vetch | AO3: yes | AQ3: Legume | AR3: Bean/Beet/Corn/Bean | AS3: MTT | AU3: Not reported | AV3: yes | AX3: yes | BK3: CC | BM3: Fallow | GP3: Not reported | GT3: 6.6 | GU3: 6 | GX3: Root diseases determined by root rot, ranged from 1(no root rot observed) to 9 (80% roots infected) | JU3: Root infected by rot
A4: 3 | B4: SoilHealthDB_V2_Jian et al | C4: 1 | D4: 1-2 | E4: Abawi | G4: G.S. | H4: 2000 | J4: Applied Soil Ecology | K4: New York | L4: USA | M4: 40.71 | N4: -74.01 | O4: 3.5 | Z4: Not-available | AA4: Not-available | AH4: NotAvailable | AN4: White_mustard | AO4: yes | AQ4: Brassica | AR4: Bean/Beet/Corn/Bean | AS4: MTT | AU4: Not reported | AV4: yes | AX4: yes | BK4: CC | BM4: Fallow | CB4: 4862 | CC4: =3990 -> 3990 | GP4: Not reported | GT4: 6.6 | GU4: 5.9 | GX4: Root diseases determined by root rot, ranged from 1(no root rot observed) to 9 (80% roots infected) | JU4: Root infected by rot
A5: 4 | B5: SoilHealthDB_V2_Jian et al | C5: 1 | D5: 1-1 | E5: Abawi | G5: G.S. | H5: 2000 | J5: Applied Soil Ecology | K5: New York | L5: USA | M5: 40.71 | N5: -74.01 | O5: 3.5 | Z5: Not-available | AA5: Not-available | AH5: NotAvailable | AN5: Alfalfa | AO5: yes | AQ5: Legume | AR5: Bean/Beet/Corn/Bean | AS5: MTT | AU5: Not reported | AV5: yes | AX5: yes | BK5: CC | BM5: Fallow | GP5: Not reported | GT5: 6.6 | GU5: 5.7 | GX5: Root diseases determined by root rot, ranged from 1(no root rot observed) to 9 (80% roots infected) | JU5: Root infected by rot
A6: 5 | B6: SoilHealthDB_V2_Jian et al | C6: 1 | D6: 1-4 | E6: Abawi | G6: G.S. | H6: 2000 | J6: Applied Soil Ecology | K6: New York | L6: USA | M6: 40.71 | N6: -74.01 | O6: 3.5 | Z6: Not-available | AA6: Not-available | AH6: NotAvailable | AN6: Ryegrass | AO6: yes | AQ6: Rye | AR6: Bean/Beet/Corn/Bean | AS6: MTT | AU6: Not reported | AV6: yes | AX6: yes | BK6: CC | BM6: Fallow | GP6: Not reported | GT6: 6.6 | GU6: 5.6 | GX6: Root diseases determined by root rot, ranged from 1(no root rot observed) to 9 (80% roots infected) | JU6: Root infected by rot
A7: 6 | B7: SoilHealthDB_V2_Jian et al | C7: 1 | D7: 1-4 | E7: Abawi | G7: G.S. | H7: 2000 | J7: Applied Soil Ecology | K7: New York | L7: USA | M7: 40.71 | N7: -74.01 | O7: 3.5 | Z7: Not-available | AA7: Not-available | AH7: NotAvailable | AN7: Oat | AO7: yes | AQ7: Grass | AR7: Bean/Beet/Corn/Bean | AS7: MTT | AU7: Not reported | AV7: yes | AX7: yes | BK7: CC | BM7: Fallow | GP7: Not reported | GT7: 6.6 | GU7: 5.2 | GX7: Root diseases determined by root rot, ranged from 1(no root rot observed) to 9 (80% roots infected) | JU7: Root infected by rot
A8: 7 | B8: SoilHealthDB_V2_Jian et al | C8: 1 | D8: 1-4 | E8: Abawi | G8: G.S. | H8: 2000 | J8: Applied Soil Ecology | K8: New York | L8: USA | M8: 40.71 | N8: -74.01 | O8: 3.5 | Z8: Not-available | AA8: Not-available | AH8: NotAvailable | AN8: Trudan_8 | AO8: yes | AQ8: Grass | AR8: Bean/Beet/Corn/Bean | AS8: MTT | AU8: Not reported | AV8: yes | AX8: yes | BK8: CC | BM8: Fallow | GP8: Not reported | GT8: 6.6 | GU8: 4.9 | GX8: Root diseases determined by root rot, ranged from 1(no root rot observed) to 9 (80% roots infected) | JU8: Root infected by rot
A9: 8 | B9: SoilHealthDB_V2_Jian et al | C9: 1 | D9: 1-4 | E9: Abawi | G9: G.S. | H9: 2000 | J9: Applied Soil Ecology | K9: New York | L9: USA | M9: 40.71 | N9: -74.01 | O9: 3.5 | Z9: Not-available | AA9: Not-available | AH9: NotAvailable | AN9: Rye_grain | AO9: yes | AQ9: Rye | AR9: Bean/Beet/Corn/Bean | AS9: MTT | AU9: Not reported | AV9: yes | AX9: yes | BK9: CC | BM9: Fallow | CB9: 4862 | CC9: 5240 | GP9: Not reported | GT9: 6.6 | GU9: 4.7 | GX9: Root diseases determined by root rot, ranged from 1(no root rot observed) to 9 (80% roots infected) | JU9: Root infected by rot
A10: 9 | B10: SoilHealthDB_V2_Jian et al | C10: 1 | D10: 1-4 | E10: Abawi | G10: G.S. | H10: 2000 | J10: Applied Soil Ecology | K10: New York | L10: USA | M10: 40.71 | N10: -74.01 | O10: 3.5 | Z10: Not-available | AA10: Not-available | AH10: NotAvailable | AN10: Wheat | AO10: yes | AQ10: Grass | AR10: Bean/Beet/Corn/Bean | AS10: MTT | AU10: Not reported | AV10: yes | AX10: yes | BK10: CC | BM10: Fallow | GP10: Not reported | GT10: 6.6 | GU10: 4.6 | GX10: Root diseases determined by root rot, ranged from 1(no root rot observed) to 9 (80% roots infected) | JU10: Root infected by rot
A11: 10 | B11: SoilHealthDB_V2_Jian et al | C11: 1 | D11: 1-1 | E11: Abawi | G11: G.S. | H11: 2000 | J11: Applied Soil Ecology | K11: New York | L11: USA | M11: 40.71 | N11: -74.01 | O11: 3.5 | Z11: Not-available | AA11: Not-available | AH11: NotAvailable | AN11: Crown_Vetch | AO11: yes | AQ11: Legume | AR11: Bean/Beet/Corn/Bean | AS11: MTT | AU11: Not reported | AV11: yes | AX11: yes | BK11: CC | BM11: Fallow | GP11: Not reported | GT11: 6.6 | GU11: 4.3 | GX11: Root diseases determined by root rot, ranged from 1(no root rot observed) to 9 (80% roots infected) | JU11: Root infected by rot
A12: 11 | B12: SoilHealthDB_V2_Jian et al | C12: 1 | D12: 1-2 | E12: Abawi | G12: G.S. | H12: 2000 | J12: Applied Soil Ecology | K12: New York | L12: USA | M12: 40.71 | N12: -74.01 | O12: 3.5 | Z12: Not-available | AA12: Not-available | AH12: NotAvailable | AN12: Rapeseed | AO12: yes | AQ12: Brassica | AR12: Bean/Beet/Corn/Bean | AS12: MTT | AU12: Not reported | AV12: yes | AX12: yes | BK12: CC | BM12: Fallow | GP12: Not reported | GT12: 6.6 | GU12: 3.9 | GX12: Root diseases determined by root rot, ranged from 1(no root rot observed) to 9 (80% roots infected) | JU12: Root infected by rot
A13: 12 | B13: SoilHealthDB_V2_Jian et al | C13: 2 | D13: 2-1 | E13: Bandic | G13: Anna | H13: 1999 | I13: 1994 | J13: Soil Biology and Biochemistry | K13: North Willamette Research and Extension Center, Aurora, Oregon | L13: USA | M13: 45.231 | N13: -122.756 | O13: 48.4 | S13: 1040 | T13: Mediterranean | U13: 6 | V13: 6 | Y13: 1989-1994, Fall, before planting of cover crop | Z13: 0-to-20 | AA13: 20 | AB13: 15.6 | AC13: Cmolc / kg | AE13: 31.3 | AF13: 54 | AH13: Silt loam | AM13: Pachic Ultic Argixeroll | AN13: Rye | AO13: yes | AQ13: Rye | AR13: Corn/Wheat/Broccoli | AS13: MTT | AT13: Vegetable crop rotation | AU13: yes | AV13: yes | AW13: Vegetable crop rotation | AX13: yes | AY13: No | BE13: Varied | BG13: Yes | BH13: Varied | BI13: Yes | BK13: CC | BM13: Fallow | BN13: 2 | BO13: 2 | BQ13: RCBD | CM13: 3.93 | CN13: 3.43 | CQ13: Organic Matter | DA13: OM (Percentage) | DB13: 971 | DC13: 947 | DF13: TN | DQ13: 5.75 | DR13: 5.83 | DV13: 15.6 | DW13: 15.2 | GP13: Not reported | JG13: 140 | JH13: 177
A14: 13 | B14: SoilHealthDB_V2_Jian et al | C14: 2 | D14: 2-2 | E14: Bandic | G14: Anna | H14: 1999 | I14: 1994 | J14: Soil Biology and Biochemistry | K14: North Willamette Research and Extension Center, Aurora, Oregon | L14: USA | M14: 45.231 | N14: -122.756 | O14: 48.4 | S14: 1040 | T14: Mediterranean | U14: 6 | V14: 6 | Y14: 1989-1994, Fall, before planting of cover crop | Z14: 0-to-20 | AA14: 20 | AB14: 15.6 | AC14: Cmolc / kg | AE14: 31.3 | AF14: 54 | AH14: Silt loam | AM14: Pachic Ultic Argixeroll | AN14: Red_clover | AO14: yes | AQ14: Legume | AR14: Corn/Wheat/Broccoli | AS14: MTT | AT14: Vegetable crop rotation | AU14: yes | AV14: yes | AW14: Vegetable crop rotation | AX14: yes | AY14: No | BE14: Varied | BG14: Yes | BH14: Varied | BI14: Yes | BK14: CC | BM14: Fallow | BN14: 2 | BO14: 2 | BQ14: RCBD | CM14: 3.93 | CN14: 4.13 | CQ14: Organic Matter | DA14: OM (Percentage) | DB14: 971 | DC14: 1120 | DF14: TN | DQ14: 5.75 | DR14: 5.9 | DV14: 15.6 | DW14: 15 | GP14: Not reported | JG14: 140 | JH14: 158
A15: 14 | B15: SoilHealthDB_V2_Jian et al | C15: 3 | D15: 3-1 | E15: Blackshaw | G15: R.E. | H15: 2008 | I15: 2003 | J15: Crop Protection | K15: Lethbridge, AB, Canada | L15: Canada | M15: 49.69 | N15: -112.84 | O15: 901 | U15: 1 | V15: 3 | Y15: 2003-2005 | Z15: Not-available | AA15: Not-available | AE15: 37 | AF15: 30 | AH15: Loam | AM15: Haplustoll | AN15: Rye_Fall_seeded_winter | AO15: yes | AQ15: Rye | AR15: Dry_bean | AS15: Vegetable | AU15: Not reported | AV15: No | AX15: No | BK15: CC | BM15: Fallow | BN15: 4 | BO15: 4 | BQ15: RCBD | BR15: 5520 | BV15: No herbicide | CB15: 16400 | CC15: 23300 | GN15: 17250 | GO15: 7310 | GP15: yes
A16: 15 | B16: SoilHealthDB_V2_Jian et al | C16: 3 | D16: 3-2 | E16: Blackshaw | G16: R.E. | H16: 2008 | I16: 2003 | J16: Crop Protection | K16: Lethbridge, AB, Canada | L16: Canada | M16: 49.69 | N16: -112.84 | O16: 901 | U16: 1 | V16: 3 | Y16: 2003-2005 | Z16: Not-available | AA16: Not-available | AE16: 37 | AF16: 30 | AH16: Loam | AM16: Haplustoll | AN16: Barley_Fall_seeded | AO16: yes | AQ16: Grass | AR16: Dry_bean | AS16: Vegetable | AU16: Not reported | AV16: No | AX16: No | BK16: CC | BM16: Fallow | BN16: 4 | BO16: 4 | BQ16: RCBD | BR16: 1320 | BV16: No herbicide | CB16: 16400 | CC16: 19800 | GN16: 17250 | GO16: 12510 | GP16: yes
A17: 16 | B17: SoilHealthDB_V2_Jian et al | C17: 3 | D17: 3-2 | E17: Blackshaw | G17: R.E. | H17: 2008 | I17: 2003 | J17: Crop Protection | K17: Lethbridge, AB, Canada | L17: Canada | M17: 49.69 | N17: -112.84 | O17: 901 | U17: 1 | V17: 3 | Y17: 2003-2005 | Z17: Not-available | AA17: Not-available | AE17: 37 | AF17: 30 | AH17: Loam | AM17: Haplustoll | AN17: Oat_Fall_seeded | AO17: yes | AQ17: Grass | AR17: Dry_bean | AS17: Vegetable | AU17: Not reported | AV17: No | AX17: No | BK17: CC | BM17: Fallow | BN17: 4 | BO17: 4 | BQ17: RCBD | BR17: 1170 | BV17: No herbicide | CB17: 16400 | CC17: 19600 | GN17: 17250 | GO17: 12180 | GP17: yes
A18: 17 | B18: SoilHealthDB_V2_Jian et al | C18: 3 | D18: 3-1 | E18: Blackshaw | G18: R.E. | H18: 2008 | I18: 2003 | J18: Crop Protection | K18: Lethbridge, AB, Canada | L18: Canada | M18: 49.69 | N18: -112.84 | O18: 901 | U18: 1 | V18: 3 | Y18: 2003-2005 | Z18: Not-available | AA18: Not-available | AE18: 37 | AF18: 30 | AH18: Loam | AM18: Haplustoll | AN18: Rye_Fall_seeded_spring | AO18: yes | AQ18: Rye | AR18: Dry_bean | AS18: Vegetable | AU18: Not reported | AV18: No | AX18: No | BK18: CC | BM18: Fallow | BN18: 4 | BO18: 4 | BQ18: RCBD | BR18: 1480 | BV18: No herbicide | CB18: 16400 | CC18: 21400 | GN18: 17250 | GO18: 11460 | GP18: yes
A19: 18 | B19: SoilHealthDB_V2_Jian et al | C19: 3 | D19: 3-2 | E19: Blackshaw | G19: R.E. | H19: 2008 | I19: 2003 | J19: Crop Protection | K19: Lethbridge, AB, Canada | L19: Canada | M19: 49.69 | N19: -112.84 | O19: 901 | U19: 1 | V19: 3 | Y19: 2003-2005 | Z19: Not-available | AA19: Not-available | AE19: 37 | AF19: 30 | AH19: Loam | AM19: Haplustoll | AN19: Barley_Spring_seeded | AO19: yes | AQ19: Grass | AR19: Dry_bean | AS19: Vegetable | AU19: Not reported | AV19: No | AX19: No | BK19: CC | BM19: Fallow | BN19: 4 | BO19: 4 | BQ19: RCBD | BR19: 690 | BV19: No herbicide | CB19: 16400 | CC19: 18000 | GN19: 17250 | GO19: 15440 | GP19: yes
A20: 19 | B20: SoilHealthDB_V2_Jian et al | C20: 3 | D20: 3-2 | E20: Blackshaw | G20: R.E. | H20: 2008 | I20: 2003 | J20: Crop Protection | K20: Lethbridge, AB, Canada | L20: Canada | M20: 49.69 | N20: -112.84 | O20: 901 | U20: 1 | V20: 3 | Y20: 2003-2005 | Z20: Not-available | AA20: Not-available | AE20: 37 | AF20: 30 | AH20: Loam | AM20: Haplustoll | AN20: Oat_Spring_seeded | AO20: yes | AQ20: Grass | AR20: Dry_bean | AS20: Vegetable | AU20: Not reported | AV20: No | AX20: No | BK20: CC | BM20: Fallow | BN20: 4 | BO20: 4 | BQ20: RCBD | BR20: 400 | BV20: No herbicide | CB20: 16400 | CC20: 19100 | GN20: 17250 | GO20: 12600 | GP20: yes
A21: 20 | B21: SoilHealthDB_V2_Jian et al | C21: 3 | D21: 3-1 | E21: Blackshaw | G21: R.E. | H21: 2008 | I21: 2003 | J21: Crop Protection | K21: Lethbridge, AB, Canada | L21: Canada | M21: 49.69 | N21: -112.84 | O21: 901 | U21: 1 | V21: 3 | Y21: 2003-2005 | Z21: Not-available | AA21: Not-available | AE21: 37 | AF21: 30 | AH21: Loam | AM21: Haplustoll | AN21: Rye_Spring_seeded_spring | AO21: yes | AQ21: Rye | AR21: Dry_bean | AS21: Vegetable | AU21: Not reported | AV21: No | AX21: No | BK21: CC | BM21: Fallow | BN21: 4 | BO21: 4 | BQ21: RCBD | BR21: 470 | BV21: No herbicide | CB21: 16400 | CC21: 18700 | GN21: 17250 | GO21: 14400 | GP21: yes
A22: 21 | B22: SoilHealthDB_V2_Jian et al | C22: 3 | D22: 3-1 | E22: Blackshaw | G22: R.E. | H22: 2008 | I22: 2004 | J22: Crop Protection | K22: Lethbridge, AB, Canada | L22: Canada | M22: 49.69 | N22: -112.84 | O22: 901 | U22: 2 | V22: 3 | Y22: 2003-2005 | Z22: Not-available | AA22: Not-available | AE22: 37 | AF22: 30 | AH22: Loam | AM22: Haplustoll | AN22: Rye_Fall_seeded_winter | AO22: yes | AQ22: Rye | AR22: Dry_bean | AS22: Vegetable | AU22: Not reported | AV22: No | AX22: No | BK22: CC | BM22: Fallow | BN22: 4 | BO22: 4 | BQ22: RCBD | BR22: 6320 | BV22: No herbicide | CB22: 11200 | CC22: 15100 | GN22: 14530 | GO22: 6600 | GP22: yes
A23: 22 | B23: SoilHealthDB_V2_Jian et al | C23: 3 | D23: 3-2 | E23: Blackshaw | G23: R.E. | H23: 2008 | I23: 2004 | J23: Crop Protection | K23: Lethbridge, AB, Canada | L23: Canada | M23: 49.69 | N23: -112.84 | O23: 901 | U23: 2 | V23: 3 | Y23: 2003-2005 | Z23: Not-available | AA23: Not-available | AE23: 37 | AF23: 30 | AH23: Loam | AM23: Haplustoll | AN23: Barley_Fall_seeded | AO23: yes | AQ23: Grass | AR23: Dry_bean | AS23: Vegetable | AU23: Not reported | AV23: No | AX23: No | BK23: CC | BM23: Fallow | BN23: 4 | BO23: 4 | BQ23: RCBD | BR23: 990 | BV23: No herbicide | CB23: 11200 | CC23: 12700 | GN23: 14530 | GO23: 11830 | GP23: yes
A24: 23 | B24: SoilHealthDB_V2_Jian et al | C24: 3 | D24: 3-2 | E24: Blackshaw | G24: R.E. | H24: 2008 | I24: 2004 | J24: Crop Protection | K24: Lethbridge, AB, Canada | L24: Canada | M24: 49.69 | N24: -112.84 | O24: 901 | U24: 2 | V24: 3 | Y24: 2003-2005 | Z24: Not-available | AA24: Not-available | AE24: 37 | AF24: 30 | AH24: Loam | AM24: Haplustoll | AN24: Oat_Fall_seeded | AO24: yes | AQ24: Grass | AR24: Dry_bean | AS24: Vegetable | AU24: Not reported | AV24: No | AX24: No | BK24: CC | BM24: Fallow | BN24: 4 | BO24: 4 | BQ24: RCBD | BR24: 1070 | BV24: No herbicide | CB24: 11200 | CC24: 13600 | GN24: 14530 | GO24: 10700 | GP24: yes
A25: 24 | B25: SoilHealthDB_V2_Jian et al | C25: 3 | D25: 3-1 | E25: Blackshaw | G25: R.E. | H25: 2008 | I25: 2004 | J25: Crop Protection | K25: Lethbridge, AB, Canada | L25: Canada | M25: 49.69 | N25: -112.84 | O25: 901 | U25: 2 | V25: 3 | Y25: 2003-2005 | Z25: Not-available | AA25: Not-available | AE25: 37 | AF25: 30 | AH25: Loam | AM25: Haplustoll | AN25: Rye_Fall_seeded_spring | AO25: yes | AQ25: Rye | AR25: Dry_bean | AS25: Vegetable | AU25: Not reported | AV25: No | AX25: No | BK25: CC | BM25: Fallow | BN25: 4 | BO25: 4 | BQ25: RCBD | BR25: 1130 | BV25: No herbicide | CB25: 11200 | CC25: 12900 | GN25: 14530 | GO25: 9940 | GP25: yes
A26: 25 | B26: SoilHealthDB_V2_Jian et al | C26: 3 | D26: 3-2 | E26: Blackshaw | G26: R.E. | H26: 2008 | I26: 2004 | J26: Crop Protection | K26: Lethbridge, AB, Canada | L26: Canada | M26: 49.69 | N26: -112.84 | O26: 901 | U26: 2 | V26: 3 | Y26: 2003-2005 | Z26: Not-available | AA26: Not-available | AE26: 37 | AF26: 30 | AH26: Loam | AM26: Haplustoll | AN26: Barley_Spring_seeded | AO26: yes | AQ26: Grass | AR26: Dry_bean | AS26: Vegetable | AU26: Not reported | AV26: No | AX26: No | BK26: CC | BM26: Fallow | BN26: 4 | BO26: 4 | BQ26: RCBD | BR26: 560 | BV26: No herbicide | CB26: 11200 | CC26: 11400 | GN26: 14530 | GO26: 14000 | GP26: yes
... A56: 55 | B56: SoilHealthDB_V2_Jian et al | C56: 3 | D56: 3-1 | E56: Blackshaw | G56: R.E. | H56: 2008 | I56: 2005 | J56: Crop Protection | K56: Lethbridge, AB, Canada | L56: Canada | M56: 49.69 | N56: -112.84 | O56: 901 | U56: 3 | V56: 3 | Y56: 2003-2005 | Z56: Not-available | AA56: Not-available | AE56: 37 | AF56: 30 | AH56: Loam | AM56: Haplustoll | AN56: Rye_Spring_seeded_spring | AO56: yes | AQ56: Rye | AR56: Dry_bean | AS56: Vegetable | AU56: Not reported | AV56: No | AX56: No | BK56: CC | BM56: Fallow | BN56: 4 | BO56: 4 | BQ56: RCBD | BR56: 230 | BV56: With herbicide | CB56: 33100 | CC56: 30500 | GN56: 2460 | GO56: 2070 | GP56: yes
A57: 56 | B57: SoilHealthDB_V2_Jian et al | C57: 4 | D57: 4-1 | E57: Blanco-Canqui | G57: Humberto | H57: 2010 | I57: =(1995+2009)/2 -> 2002 | J57: Soil and Water Management and Conservation | K57: Hesston, KS | L57: USA | M57: 38.14 | N57: -97.43 | O57: 450 | Q57: 14.4 | S57: 874 | U57: 7 | V57: 15 | Y57: 1995-2009 | Z57: 0-to-7.5 | AA57: 7.5 | AD57: 1.698 | AH57: Silt loam | AM57: Udic Argiustoll | AN57: Soybean | AO57: yes | AQ57: Legume | AR57: Winter_wheat/Sorghum | AS57: WO | AT57: Wheat-grain sorghum rotation | AU57: yes | AV57: yes | AW57: Wheat-grain sorghum rotation | AX57: yes | AY57: No | AZ57: No tillage | BA57: No tillage | BB57: NT | BC57: NT | BD57: No | BE57: 0 kg N per ha | BG57: Yes | BH57: 0 kg N per ha | BI57: Yes | BJ57: No | BK57: CC-NT | BM57: No cover crop | BN57: 4 | BO57: 4 | BQ57: RCBD | CH57: 1.698 | CI57: 1.6326 | CM57: =13.681/10 -> 1.3681 | CN57: =16.9325/10 -> 1.69325 | CQ57: SOC | DA57: SOC (Percentage) | EK57: 24 | EL57: 44 | EO57: 4.75-2 mm | EU57: 0.8613 | EV57: 0.8074 | EY57: Penetration resistance | EZ57: =(1.1169+4.1126+5.577+10.9731)/4 -> 5.4449 | FA57: =(0.4534+10.1059+14.3185+18.7023)/4 -> 10.895025 | FD57: Cummulative water infiltration (cm) Figure 7 panel B | FY57: 21.8176 | FZ57: 18.3542 | GD57: 15.68 | GE57: 16.837 | GP57: Not reported | HD57: 92.7 | HE57: 372.7 | HH57: Number of earthwarm | JU57: Earthwarm, 4.75-2 mm water stable aggregates, percentage of soil remaining in sieves, other 5 indicator available | JW57: Winter CC (planed in the fall)
A58: 57 | B58: SoilHealthDB_V2_Jian et al | C58: 4 | D58: 4-2 | E58: Blanco-Canqui | G58: Humberto | H58: 2010 | I58: =(1995+2009)/2 -> 2002 | J58: Soil and Water Management and Conservation | K58: Hesston, KS | L58: USA | M58: 38.14 | N58: -97.43 | O58: 450 | Q58: 14.4 | S58: 874 | U58: 7 | V58: 15 | Y58: 1995-2009 | Z58: 7.5-to-15 | AA58: 7.5 | AD58: 1.6915 | AH58: Silt loam | AM58: Udic Argiustoll | AN58: Soybean | AO58: yes | AQ58: Legume | AR58: Winter_wheat/Sorghum | AS58: WO | AT58: Wheat-grain sorghum rotation | AU58: yes | AV58: yes | AW58: Wheat-grain sorghum rotation | AX58: yes | AY58: No | AZ58: No tillage | BA58: No tillage | BB58: NT | BC58: NT | BD58: No | BE58: 0 kg N per ha | BG58: Yes | BH58: 0 kg N per ha | BI58: Yes | BJ58: No | BK58: CC-NT | BM58: No cover crop | BN58: 4 | BO58: 4 | BQ58: RCBD | CH58: 1.6915 | CI58: 1.6998 | CM58: =10.3067/10 -> 1.03067 | CN58: =10.7055/10 -> 1.07055 | CQ58: SOC | DA58: SOC (Percentage) | EK58: 14 | EL58: 24 | EO58: 4.75-2 mm | EU58: 0.8613 | EV58: =(1.0549+0.9738)/2 -> 1.01435 | EY58: Penetration resistance | EZ58: =(1.12+3.14+5.7)/3 -> 3.32 | FA58: =(1.88+6.2+11.22)/3 -> 6.4333333 | FD58: Cummulative water infiltration (cm) Figure 7 panel A | FY58: 18.5625 | FZ58: 16.0104 | GD58: 15.21 | GE58: 16.279 | GP58: Not reported | JU58: Earthwarm, 4.75-2 mm water stable aggregates, percentage of soil remaining in sieves, other 5 indicator available | JW58: Winter CC (planed in the fall)
A59: 58 | B59: SoilHealthDB_V2_Jian et al | C59: 4 | D59: 4-1 | E59: Blanco-Canqui | G59: Humberto | H59: 2010 | I59: =(1995+2009)/2 -> 2002 | J59: Soil and Water Management and Conservation | K59: Hesston, KS | L59: USA | M59: 38.14 | N59: -97.43 | O59: 450 | Q59: 14.4 | S59: 874 | U59: 7 | V59: 15 | Y59: 1995-2009 | Z59: 0-to-7.5 | AA59: 7.5 | AD59: 1.698 | AH59: Silt loam | AM59: Udic Argiustoll | AN59: Hemp | AO59: yes | AQ59: Legume | AR59: Winter_wheat/Sorghum | AS59: WO | AT59: Wheat-grain sorghum rotation | AU59: yes | AV59: yes | AW59: Wheat-grain sorghum rotation | AX59: yes | AY59: No | AZ59: No tillage | BA59: No tillage | BB59: NT | BC59: NT | BD59: No | BE59: 0 kg N per ha | BG59: Yes | BH59: 0 kg N per ha | BI59: Yes | BJ59: No | BK59: CC-NT | BM59: No cover crop | BN59: 4 | BO59: 4 | BQ59: RCBD | CH59: 1.698 | CI59: 1.6104 | CM59: =13.681/10 -> 1.3681 | CN59: =18.1595/10 -> 1.81595 | CQ59: SOC | DA59: SOC (Percentage) | EK59: 24 | EL59: 41 | EO59: 4.75-2 mm | EU59: 0.8613 | EV59: 0.8934 | EY59: Penetration resistance | EZ59: =(1.1169+4.1126+5.577+10.9731)/4 -> 5.4449 | FA59: =(5.8369+13.6663+17.0158+24.68)/4 -> 15.29975 | FD59: Cummulative water infiltration (cm) Figure 7 panel B | FY59: 21.8176 | FZ59: 18.1979 | GD59: 15.68 | GE59: 17.727 | GP59: Not reported | HD59: 92.7 | HE59: 623.6 | HH59: Number of earthwarm | JU59: Earthwarm, 4.75-2 mm water stable aggregates, percentage of soil remaining in sieves, other 5 indicator available | JW59: Winter CC (planed in the fall)
A60: 59 | B60: SoilHealthDB_V2_Jian et al | C60: 4 | D60: 4-2 | E60: Blanco-Canqui | G60: Humberto | H60: 2010 | I60: =(1995+2009)/2 -> 2002 | J60: Soil and Water Management and Conservation | K60: Hesston, KS | L60: USA | M60: 38.14 | N60: -97.43 | O60: 450 | Q60: 14.4 | S60: 874 | U60: 7 | V60: 15 | Y60: 1995-2009 | Z60: 7.5-to-15 | AA60: 7.5 | AD60: 1.6915 | AH60: Silt loam | AM60: Udic Argiustoll | AN60: Hemp | AO60: yes | AQ60: Legume | AR60: Winter_wheat/Sorghum | AS60: WO | AT60: Wheat-grain sorghum rotation | AU60: yes | AV60: yes | AW60: Wheat-grain sorghum rotation | AX60: yes | AY60: No | AZ60: No tillage | BA60: No tillage | BB60: NT | BC60: NT | BD60: No | BE60: 0 kg N per ha | BG60: Yes | BH60: 0 kg N per ha | BI60: Yes | BJ60: No | BK60: CC-NT | BM60: No cover crop | BN60: 4 | BO60: 4 | BQ60: RCBD | CH60: 1.6915 | CI60: 1.6932 | CM60: =10.3067/10 -> 1.03067 | CN60: =10.6135/10 -> 1.06135 | CQ60: SOC | DA60: SOC (Percentage) | EK60: 14 | EL60: 18 | EO60: 4.75-2 mm | EU60: 0.8613 | EV60: 0.775 | EY60: Penetration resistance | EZ60: =(1.12+3.14+5.7)/3 -> 3.32 | FA60: =(1.88+7.73+15.54)/3 -> 8.3833333 | FD60: Cummulative water infiltration (cm) Figure 7 panel A | FY60: 18.5625 | FZ60: 16.2448 | GD60: 15.21 | GE60: 16.788 | GP60: Not reported | JU60: Earthwarm, 4.75-2 mm water stable aggregates, percentage of soil remaining in sieves, other 5 indicator available | JW60: Winter CC (planed in the fall)
A61: 60 | B61: SoilHealthDB_V2_Jian et al | C61: 4 | D61: 4-3 | E61: Blanco-Canqui | G61: Humberto | H61: 2010 | I61: =(1995+2009)/2 -> 2002 | J61: Soil and Water Management and Conservation | K61: Hesston, KS | L61: USA | M61: 38.14 | N61: -97.43 | O61: 450 | Q61: 14.4 | S61: 874 | U61: 7 | V61: 15 | Y61: 1995-2009 | Z61: 0-to-7.5 | AA61: 7.5 | AD61: 1.642 | AH61: Silt loam | AM61: Udic Argiustoll | AN61: Soybean | AO61: yes | AQ61: Legume | AR61: Winter_wheat/Sorghum | AS61: WO | AT61: Wheat-grain sorghum rotation | AU61: yes | AV61: yes | AW61: Wheat-grain sorghum rotation | AX61: yes | AY61: No | AZ61: No tillage | BA61: No tillage | BB61: NT | BC61: NT | BD61: No | BE61: 66 kg N per ha | BF61: Yes | BG61: Yes | BH61: 66 kg N per ha | BI61: Yes | BJ61: No | BK61: CC-NT | BM61: No cover crop | BN61: 4 | BO61: 4 | BQ61: RCBD | CH61: 1.642 | CI61: 1.6059 | CM61: =13.681/10 -> 1.3681 | CN61: =17.3313/10 -> 1.73313 | CQ61: SOC | DA61: SOC (Percentage) | EK61: 115 | EL61: 138 | EO61: 0.5-0.25 mm agg | GD61: =0.1693*100 -> 16.93 | GE61: =0.18*100 -> 18 | GP61: Not reported | JU61: Earthwarm, 4.75-2 mm water stable aggregates, percentage of soil remaining in sieves, other 5 indicator available | JW61: Winter CC (planed in the fall)
A62: 61 | B62: SoilHealthDB_V2_Jian et al | C62: 4 | D62: 4-4 | E62: Blanco-Canqui | G62: Humberto | H62: 2010 | I62: =(1995+2009)/2 -> 2002 | J62: Soil and Water Management and Conservation | K62: Hesston, KS | L62: USA | M62: 38.14 | N62: -97.43 | O62: 450 | Q62: 14.4 | S62: 874 | U62: 7 | V62: 15 | Y62: 1995-2009 | Z62: 7.5-to-15 | AA62: 7.5 | AD62: 1.7102 | AH62: Silt loam | AM62: Udic Argiustoll | AN62: Soybean | AO62: yes | AQ62: Legume | AR62: Winter_wheat/Sorghum | AS62: WO | AT62: Wheat-grain sorghum rotation | AU62: yes | AV62: yes | AW62: Wheat-grain sorghum rotation | AX62: yes | AY62: No | AZ62: No tillage | BA62: No tillage | BB62: NT | BC62: NT | BD62: No | BE62: 66 kg N per ha | BF62: Yes | BG62: Yes | BH62: 66 kg N per ha | BI62: Yes | BJ62: No | BK62: CC-NT | BM62: No cover crop | BN62: 4 | BO62: 4 | BQ62: RCBD | CH62: 1.7102 | CI62: 1.6938 | CM62: =10.3067/10 -> 1.03067 | CN62: =10.2147/10 -> 1.02147 | CQ62: SOC | DA62: SOC (Percentage) | EK62: 172 | EL62: 170 | EO62: 0.5-0.25 mm agg | GD62: =0.1611*100 -> 16.11 | GE62: =0.1619*100 -> 16.19 | GP62: Not reported | JU62: Earthwarm, 4.75-2 mm water stable aggregates, percentage of soil remaining in sieves, other 5 indicator available | JW62: Winter CC (planed in the fall)
A63: 62 | B63: SoilHealthDB_V2_Jian et al | C63: 4 | D63: 4-3 | E63: Blanco-Canqui | G63: Humberto | H63: 2010 | I63: =(1995+2009)/2 -> 2002 | J63: Soil and Water Management and Conservation | K63: Hesston, KS | L63: USA | M63: 38.14 | N63: -97.43 | O63: 450 | Q63: 14.4 | S63: 874 | U63: 7 | V63: 15 | Y63: 1995-2009 | Z63: 0-to-7.5 | AA63: 7.5 | AD63: 1.642 | AH63: Silt loam | AM63: Udic Argiustoll | AN63: Hemp | AO63: yes | AQ63: Legume | AR63: Winter_wheat/Sorghum | AS63: WO | AT63: Wheat-grain sorghum rotation | AU63: yes | AV63: yes | AW63: Wheat-grain sorghum rotation | AX63: yes | AY63: No | AZ63: No tillage | BA63: No tillage | BB63: NT | BC63: NT | BD63: No | BE63: 66 kg N per ha | BF63: Yes | BG63: Yes | BH63: 66 kg N per ha | BI63: Yes | BJ63: No | BK63: CC-NT | BM63: No cover crop | BN63: 4 | BO63: 4 | BQ63: RCBD | CH63: 1.642 | CI63: 1.6193 | CM63: =13.681/10 -> 1.3681 | CN63: =17.3313/10 -> 1.73313 | CQ63: SOC | DA63: SOC (Percentage) | EK63: 115 | EL63: 149 | EO63: 0.5-0.25 mm agg | GD63: =0.1693*100 -> 16.93 | GE63: =0.1774*100 -> 17.74 | GP63: Not reported | JU63: Earthwarm, 4.75-2 mm water stable aggregates, percentage of soil remaining in sieves, other 5 indicator available | JW63: Winter CC (planed in the fall)
A64: 63 | B64: SoilHealthDB_V2_Jian et al | C64: 4 | D64: 4-4 | E64: Blanco-Canqui | G64: Humberto | H64: 2010 | I64: =(1995+2009)/2 -> 2002 | J64: Soil and Water Management and Conservation | K64: Hesston, KS | L64: USA | M64: 38.14 | N64: -97.43 | O64: 450 | Q64: 14.4 | S64: 874 | U64: 7 | V64: 15 | Y64: 1995-2009 | Z64: 7.5-to-15 | AA64: 7.5 | AD64: 1.7102 | AH64: Silt loam | AM64: Udic Argiustoll | AN64: Hemp | AO64: yes | AQ64: Legume | AR64: Winter_wheat/Sorghum | AS64: WO | AT64: Wheat-grain sorghum rotation | AU64: yes | AV64: yes | AW64: Wheat-grain sorghum rotation | AX64: yes | AY64: No | AZ64: No tillage | BA64: No tillage | BB64: NT | BC64: NT | BD64: No | BE64: 66 kg N per ha | BF64: Yes | BG64: Yes | BH64: 66 kg N per ha | BI64: Yes | BJ64: No | BK64: CC-NT | BM64: No cover crop | BN64: 4 | BO64: 4 | BQ64: RCBD | CH64: 1.7102 | CI64: 1.6987 | CM64: =10.3067/10 -> 1.03067 | CN64: =10.2147/10 -> 1.02147 | CQ64: SOC | DA64: SOC (Percentage) | EK64: 172 | EL64: 169 | EO64: 0.5-0.25 mm agg | GD64: =0.1611*100 -> 16.11 | GE64: =0.1671*100 -> 16.71 | GP64: Not reported | JU64: Earthwarm, 4.75-2 mm water stable aggregates, percentage of soil remaining in sieves, other 5 indicator available | JW64: Winter CC (planed in the fall)
A65: 64 | B65: SoilHealthDB_V2_Jian et al | C65: 5 | D65: 5-1 | E65: Blanco-Canqui | G65: Humberto | H65: 2013 | I65: 2011 | J65: Soil and Water Management and Conservation | K65: Garden City, KS | L65: USA | M65: 37.97 | N65: -100.87 | O65: 865.6 | R65: 400 | S65: 489 | U65: 4 | V65: 5 | Y65: 2007-2012 | Z65: 0-to-7.5 | AA65: 7.5 | AD65: 1.57 | AH65: Silt loam | AM65: Aridic Haplustolls | AN65: Lentil_Winter | AO65: yes | AQ65: Legume | AR65: Winter_wheat/Crop | AS65: WO | AT65: Wheat-Crop-Fallow | AU65: yes | AV65: No | AW65: Wheat-Crop-Fallow | AX65: No | AY65: No | BK65: CC | BM65: Fallow | BN65: 4 | BO65: 4 | BQ65: Split-split-plot RCBD | CH65: 1.57 | CI65: 1.45 | CM65: =8.7/1000*100 -> 0.87 | CN65: 0.92 | CR65: 10.9 | CS65: 11.3 | CV65: SOC, Units in Mg per Ha available | DA65: SOC (Mg per Ha) | EK65: =0.5877*100 -> 58.77 | EL65: =0.4353*100 -> 43.53 | EO65: Units (%), < 0.84 mm aggregates | FJ65: 1.5894 | FK65: 0.9649 | FN65: t/ha Sediment loess | GP65: Not reported | JU65: Geometric mean Diameter of dry aggregates, water-stable, available
A66: 65 | B66: SoilHealthDB_V2_Jian et al | C66: 5 | D66: 5-1 | E66: Blanco-Canqui | G66: Humberto | H66: 2013 | I66: 2011 | J66: Soil and Water Management and Conservation | K66: Garden City, KS | L66: USA | M66: 37.97 | N66: -100.87 | O66: 865.6 | R66: 400 | S66: 489 | U66: 4 | V66: 5 | Y66: 2007-2012 | Z66: 0-to-7.5 | AA66: 7.5 | AD66: 1.57 | AH66: Silt loam | AM66: Aridic Haplustolls | AN66: Pea_Spring | AO66: yes | AQ66: Legume | AR66: Winter_wheat/Crop | AS66: WO | AT66: Wheat-Crop-Fallow | AU66: yes | AV66: No | AW66: Wheat-Crop-Fallow | AX66: No | AY66: No | BK66: CC | BM66: Fallow | BN66: 4 | BO66: 4 | BQ66: Split-split-plot RCBD | CH66: 1.57 | CI66: 1.55 | CM66: =8.7/1000*100 -> 0.87 | CN66: 1.01 | CR66: 10.9 | CS66: 12.5 | CV66: SOC, Units in Mg per Ha available | DA66: SOC (Mg per Ha) | EK66: =0.5877*100 -> 58.77 | EL66: =0.3374*100 -> 33.74 | EO66: Units (%), < 0.84 mm aggregates | FJ66: 1.5894 | FK66: 0.5032 | FN66: t/ha Sediment loess | GP66: Not reported | JU66: Geometric mean Diameter of dry aggregates, water-stable, available
A67: 66 | B67: SoilHealthDB_V2_Jian et al | C67: 5 | D67: 5-1 | E67: Blanco-Canqui | G67: Humberto | H67: 2013 | I67: 2011 | J67: Soil and Water Management and Conservation | K67: Garden City, KS | L67: USA | M67: 37.97 | N67: -100.87 | O67: 865.6 | R67: 400 | S67: 489 | U67: 4 | V67: 5 | Y67: 2007-2012 | Z67: 0-to-7.5 | AA67: 7.5 | AD67: 1.57 | AH67: Silt loam | AM67: Aridic Haplustolls | AN67: Lentil_Spring | AO67: yes | AQ67: Legume | AR67: Winter_wheat/Crop | AS67: WO | AT67: Wheat-Crop-Fallow | AU67: yes | AV67: No | AW67: Wheat-Crop-Fallow | AX67: No | AY67: No | BK67: CC | BM67: Fallow | BN67: 4 | BO67: 4 | BQ67: Split-split-plot RCBD | CH67: 1.57 | CI67: 1.49 | CM67: =8.7/1000*100 -> 0.87 | CN67: 1.08 | CR67: 10.9 | CS67: 13.5 | CV67: SOC, Units in Mg per Ha available | DA67: SOC (Mg per Ha) | EK67: =0.5877*100 -> 58.77 | EL67: =0.423*100 -> 42.3 | EO67: Units (%), < 0.84 mm aggregates | GP67: Not reported | JU67: Geometric mean Diameter of dry aggregates, water-stable, available
A68: 67 | B68: SoilHealthDB_V2_Jian et al | C68: 5 | D68: 5-2 | E68: Blanco-Canqui | G68: Humberto | H68: 2013 | I68: 2011 | J68: Soil and Water Management and Conservation | K68: Garden City, KS | L68: USA | M68: 37.97 | N68: -100.87 | O68: 865.6 | R68: 400 | S68: 489 | U68: 4 | V68: 5 | Y68: 2007-2012 | Z68: 0-to-7.5 | AA68: 7.5 | AD68: 1.57 | AH68: Silt loam | AM68: Aridic Haplustolls | AN68: Triticale_Winter | AO68: yes | AQ68: Grass | AR68: Winter_wheat/Crop | AS68: WO | AT68: Wheat-Crop-Fallow | AU68: yes | AV68: No | AW68: Wheat-Crop-Fallow | AX68: No | AY68: No | BK68: CC | BM68: Fallow | BN68: 4 | BO68: 4 | BQ68: Split-split-plot RCBD | CH68: 1.57 | CI68: 1.39 | CM68: =8.7/1000*100 -> 0.87 | CN68: 1.14 | CR68: 10.9 | CS68: 13.4 | CV68: SOC, Units in Mg per Ha available | DA68: SOC (Mg per Ha) | EK68: =0.5877*100 -> 58.77 | EL68: =0.3939*100 -> 39.39 | EO68: Units (%), < 0.84 mm aggregates | FJ68: 1.5894 | FK68: 0.3256 | FN68: t/ha Sediment loess | GP68: Not reported | JU68: Geometric mean Diameter of dry aggregates, water-stable, available
A69: 68 | B69: SoilHealthDB_V2_Jian et al | C69: 5 | D69: 5-2 | E69: Blanco-Canqui | G69: Humberto | H69: 2013 | I69: 2011 | J69: Soil and Water Management and Conservation | K69: Garden City, KS | L69: USA | M69: 37.97 | N69: -100.87 | O69: 865.6 | R69: 400 | S69: 489 | U69: 4 | V69: 5 | Y69: 2007-2012 | Z69: 0-to-7.5 | AA69: 7.5 | AD69: 1.57 | AH69: Silt loam | AM69: Aridic Haplustolls | AN69: Triticale_Spring | AO69: yes | AQ69: Grass | AR69: Winter_wheat/Crop | AS69: WO | AT69: Wheat-Crop-Fallow | AU69: yes | AV69: No | AW69: Wheat-Crop-Fallow | AX69: No | AY69: No | BK69: CC | BM69: Fallow | BN69: 4 | BO69: 4 | BQ69: Split-split-plot RCBD | BV69: Subplot, Cover | CH69: 1.57 | CI69: 1.46 | CM69: =8.7/1000*100 -> 0.87 | CN69: 0.94 | CR69: 10.9 | CS69: 11.7 | CV69: SOC, Units in Mg per Ha available | DA69: SOC (Mg per Ha) | EK69: =0.5877*100 -> 58.77 | EL69: =0.6318*100 -> 63.18 | EO69: Units (%), < 0.84 mm aggregates | FJ69: 1.5894 | FK69: 0.6117 | FN69: t/ha Sediment loess | GP69: Not reported | JU69: Geometric mean Diameter of dry aggregates, water-stable, available
A70: 69 | B70: SoilHealthDB_V2_Jian et al | C70: 5 | D70: 5-2 | E70: Blanco-Canqui | G70: Humberto | H70: 2013 | I70: 2011 | J70: Soil and Water Management and Conservation | K70: Garden City, KS | L70: USA | M70: 37.97 | N70: -100.87 | O70: 865.6 | R70: 400 | S70: 489 | U70: 4 | V70: 5 | Y70: 2007-2012 | Z70: 0-to-7.5 | AA70: 7.5 | AD70: 1.57 | AH70: Silt loam | AM70: Aridic Haplustolls | AN70: Continus_wheat | AO70: yes | AQ70: Grass | AR70: Winter_wheat/Crop | AS70: WO | AT70: Wheat-Crop-Fallow | AU70: yes | AV70: No | AW70: Wheat-Crop-Fallow | AX70: No | AY70: No | BK70: CC | BM70: Fallow | BN70: 4 | BO70: 4 | BQ70: Split-split-plot RCBD | BV70: Subplot, Hayed | CH70: 1.57 | CI70: 1.44 | CM70: =8.7/1000*100 -> 0.87 | CN70: 1.16 | CR70: 10.9 | CS70: 14 | CV70: SOC, Units in Mg per Ha available | DA70: SOC (Mg per Ha) | EK70: =0.5877*100 -> 58.77 | EL70: =0.3878*100 -> 38.78 | EO70: Units (%), < 0.84 mm aggregates | GP70: Not reported | JU70: Geometric mean Diameter of dry aggregates, water-stable, available
A71: 70 | B71: SoilHealthDB_V2_Jian et al | C71: 5 | D71: 5-1 | E71: Blanco-Canqui | G71: Humberto | H71: 2013 | I71: 2011 | J71: Soil and Water Management and Conservation | K71: Garden City, KS | L71: USA | M71: 37.97 | N71: -100.87 | O71: 865.6 | R71: 400 | S71: 489 | U71: 4 | V71: 5 | Y71: 2007-2012 | Z71: 0-to-7.5 | AA71: 7.5 | AD71: 1.57 | AH71: Silt loam | AM71: Aridic Haplustolls | AN71: Lentil_Winter | AO71: yes | AQ71: Legume | AR71: Winter_wheat/Crop | AS71: WO | AT71: Wheat-Crop-Fallow | AU71: yes | AV71: No | AW71: Wheat-Crop-Fallow | AX71: No | AY71: No | BK71: CC | BM71: Fallow | BN71: 4 | BO71: 4 | BQ71: Split-split-plot RCBD | BV71: Subplot, Cover | CH71: 1.57 | CI71: 1.45 | CM71: =8.7/1000*100 -> 0.87 | CN71: 1.21 | CR71: 10.9 | CS71: 14.4 | CV71: SOC, Units in Mg per Ha available | DA71: SOC (Mg per Ha) | EK71: =0.5877*100 -> 58.77 | EL71: =0.4163*100 -> 41.63 | EO71: Units (%), < 0.84 mm aggregates | GP71: Not reported | JU71: Geometric mean Diameter of dry aggregates, water-stable, available
A72: 71 | B72: SoilHealthDB_V2_Jian et al | C72: 5 | D72: 5-1 | E72: Blanco-Canqui | G72: Humberto | H72: 2013 | I72: 2011 | J72: Soil and Water Management and Conservation | K72: Garden City, KS | L72: USA | M72: 37.97 | N72: -100.87 | O72: 865.6 | R72: 400 | S72: 489 | U72: 4 | V72: 5 | Y72: 2007-2012 | Z72: 0-to-7.5 | AA72: 7.5 | AD72: 1.57 | AH72: Silt loam | AM72: Aridic Haplustolls | AN72: Pea_Spring | AO72: yes | AQ72: Legume | AR72: Winter_wheat/Crop | AS72: WO | AT72: Wheat-Crop-Fallow | AU72: yes | AV72: No | AW72: Wheat-Crop-Fallow | AX72: No | AY72: No | BK72: CC | BM72: Fallow | BN72: 4 | BO72: 4 | BQ72: Split-split-plot RCBD | BV72: Subplot, Hayed | CH72: 1.57 | CI72: 1.45 | CM72: =8.7/1000*100 -> 0.87 | CN72: 1.3 | CR72: 10.9 | CS72: 15.6 | CV72: SOC, Units in Mg per Ha available | DA72: SOC (Mg per Ha) | EK72: =0.5877*100 -> 58.77 | EL72: =0.2698*100 -> 26.98 | EO72: Units (%), < 0.84 mm aggregates | GP72: Not reported | JU72: Geometric mean Diameter of dry aggregates, water-stable, available
A73: 72 | B73: SoilHealthDB_V2_Jian et al | C73: 5 | D73: 5-1 | E73: Blanco-Canqui | G73: Humberto | H73: 2013 | I73: 2012 | J73: Soil and Water Management and Conservation | K73: Garden City, KS | L73: USA | M73: 37.97 | N73: -100.87 | O73: 865.6 | R73: 308 | S73: 489 | U73: 5 | V73: 5 | Y73: 2007-2012 | Z73: 0-to-7.5 | AA73: 7.5 | AD73: 1.49 | AH73: Silt loam | AM73: Aridic Haplustolls | AN73: Lentil_Winter | AO73: yes | AQ73: Legume | AR73: Winter_wheat/Crop | AS73: WO | AT73: Wheat-Crop-Fallow | AU73: yes | AV73: No | AW73: Wheat-Crop-Fallow | AX73: No | AY73: No | BK73: CC | BM73: Fallow | BN73: 4 | BO73: 4 | BQ73: Split-split-plot RCBD | CH73: 1.49 | CI73: 1.4 | CM73: =8.8*100/1000 -> 0.88 | CN73: 0.93 | CR73: 9.9 | CS73: 10.4 | CV73: SOC, Units in Mg per Ha available | DA73: SOC (Mg per Ha) | GP73: Not reported | JU73: Geometric mean Diameter of dry aggregates, water-stable, available
A74: 73 | B74: SoilHealthDB_V2_Jian et al | C74: 5 | D74: 5-1 | E74: Blanco-Canqui | G74: Humberto | H74: 2013 | I74: 2012 | J74: Soil and Water Management and Conservation | K74: Garden City, KS | L74: USA | M74: 37.97 | N74: -100.87 | O74: 865.6 | R74: 308 | S74: 489 | U74: 5 | V74: 5 | Y74: 2007-2012 | Z74: 0-to-7.5 | AA74: 7.5 | AD74: 1.49 | AH74: Silt loam | AM74: Aridic Haplustolls | AN74: Pea_Spring | AO74: yes | AQ74: Legume | AR74: Winter_wheat/Crop | AS74: WO | AT74: Wheat-Crop-Fallow | AU74: yes | AV74: No | AW74: Wheat-Crop-Fallow | AX74: No | AY74: No | BK74: CC | BM74: Fallow | BN74: 4 | BO74: 4 | BQ74: Split-split-plot RCBD | CH74: 1.49 | CI74: 1.42 | CM74: =8.8*100/1000 -> 0.88 | CN74: 1.02 | CR74: 9.9 | CS74: 11.5 | CV74: SOC, Units in Mg per Ha available | DA74: SOC (Mg per Ha) | GP74: Not reported | JU74: Geometric mean Diameter of dry aggregates, water-stable, available
A75: 74 | B75: SoilHealthDB_V2_Jian et al | C75: 5 | D75: 5-1 | E75: Blanco-Canqui | G75: Humberto | H75: 2013 | I75: 2012 | J75: Soil and Water Management and Conservation | K75: Garden City, KS | L75: USA | M75: 37.97 | N75: -100.87 | O75: 865.6 | R75: 308 | S75: 489 | U75: 5 | V75: 5 | Y75: 2007-2012 | Z75: 0-to-7.5 | AA75: 7.5 | AD75: 1.49 | AH75: Silt loam | AM75: Aridic Haplustolls | AN75: Lentil_Spring | AO75: yes | AQ75: Legume | AR75: Winter_wheat/Crop | AS75: WO | AT75: Wheat-Crop-Fallow | AU75: yes | AV75: No | AW75: Wheat-Crop-Fallow | AX75: No | AY75: No | BK75: CC | BM75: Fallow | BN75: 4 | BO75: 4 | BQ75: Split-split-plot RCBD | CH75: 1.49 | CI75: 1.48 | CM75: =8.8*100/1000 -> 0.88 | CN75: 1.08 | CR75: 9.9 | CS75: 12 | CV75: SOC, Units in Mg per Ha available | DA75: SOC (Mg per Ha) | GP75: Not reported | JU75: Geometric mean Diameter of dry aggregates, water-stable, available
A76: 75 | B76: SoilHealthDB_V2_Jian et al | C76: 5 | D76: 5-2 | E76: Blanco-Canqui | G76: Humberto | H76: 2013 | I76: 2012 | J76: Soil and Water Management and Conservation | K76: Garden City, KS | L76: USA | M76: 37.97 | N76: -100.87 | O76: 865.6 | R76: 308 | S76: 489 | U76: 5 | V76: 5 | Y76: 2007-2012 | Z76: 0-to-7.5 | AA76: 7.5 | AD76: 1.49 | AH76: Silt loam | AM76: Aridic Haplustolls | AN76: Triticale_Winter | AO76: yes | AQ76: Grass | AR76: Winter_wheat/Crop | AS76: WO | AT76: Wheat-Crop-Fallow | AU76: yes | AV76: No | AW76: Wheat-Crop-Fallow | AX76: No | AY76: No | BK76: CC | BM76: Fallow | BN76: 4 | BO76: 4 | BQ76: Split-split-plot RCBD | CH76: 1.49 | CI76: 1.49 | CM76: =8.8*100/1000 -> 0.88 | CN76: 0.94 | CR76: 9.9 | CS76: 10.6 | CV76: SOC, Units in Mg per Ha available | DA76: SOC (Mg per Ha) | GP76: Not reported | JU76: Geometric mean Diameter of dry aggregates, water-stable, available
A77: 76 | B77: SoilHealthDB_V2_Jian et al | C77: 5 | D77: 5-2 | E77: Blanco-Canqui | G77: Humberto | H77: 2013 | I77: 2012 | J77: Soil and Water Management and Conservation | K77: Garden City, KS | L77: USA | M77: 37.97 | N77: -100.87 | O77: 865.6 | R77: 308 | S77: 489 | U77: 5 | V77: 5 | Y77: 2007-2012 | Z77: 0-to-7.5 | AA77: 7.5 | AD77: 1.49 | AH77: Silt loam | AM77: Aridic Haplustolls | AN77: Triticale_Spring | AO77: yes | AQ77: Grass | AR77: Winter_wheat/Crop | AS77: WO | AT77: Wheat-Crop-Fallow | AU77: yes | AV77: No | AW77: Wheat-Crop-Fallow | AX77: No | AY77: No | BK77: CC | BM77: Fallow | BN77: 4 | BO77: 4 | BQ77: Split-split-plot RCBD | BV77: Subplot, Cover | CH77: 1.49 | CI77: 1.5 | CM77: =8.8*100/1000 -> 0.88 | CN77: 0.99 | CR77: 9.9 | CS77: 11.2 | CV77: SOC, Units in Mg per Ha available | DA77: SOC (Mg per Ha) | GP77: Not reported | JU77: Geometric mean Diameter of dry aggregates, water-stable, available
A78: 77 | B78: SoilHealthDB_V2_Jian et al | C78: 5 | D78: 5-2 | E78: Blanco-Canqui | G78: Humberto | H78: 2013 | I78: 2012 | J78: Soil and Water Management and Conservation | K78: Garden City, KS | L78: USA | M78: 37.97 | N78: -100.87 | O78: 865.6 | R78: 308 | S78: 489 | U78: 5 | V78: 5 | Y78: 2007-2012 | Z78: 0-to-7.5 | AA78: 7.5 | AD78: 1.49 | AH78: Silt loam | AM78: Aridic Haplustolls | AN78: Continus_wheat | AO78: yes | AQ78: Grass | AR78: Winter_wheat/Crop | AS78: WO | AT78: Wheat-Crop-Fallow | AU78: yes | AV78: No | AW78: Wheat-Crop-Fallow | AX78: No | AY78: No | BK78: CC | BM78: Fallow | BN78: 4 | BO78: 4 | BQ78: Split-split-plot RCBD | BV78: Subplot, Hayed | CH78: 1.49 | CI78: 1.47 | CM78: =8.8*100/1000 -> 0.88 | CN78: 1.04 | CR78: 9.9 | CS78: 11.5 | CV78: SOC, Units in Mg per Ha available | DA78: SOC (Mg per Ha) | GP78: Not reported | JU78: Geometric mean Diameter of dry aggregates, water-stable, available
A79: 78 | B79: SoilHealthDB_V2_Jian et al | C79: 5 | D79: 5-1 | E79: Blanco-Canqui | G79: Humberto | H79: 2013 | I79: 2012 | J79: Soil and Water Management and Conservation | K79: Garden City, KS | L79: USA | M79: 37.97 | N79: -100.87 | O79: 865.6 | R79: 308 | S79: 489 | U79: 5 | V79: 5 | Y79: 2007-2012 | Z79: 0-to-7.5 | AA79: 7.5 | AD79: 1.49 | AH79: Silt loam | AM79: Aridic Haplustolls | AN79: Lentil_Winter | AO79: yes | AQ79: Legume | AR79: Winter_wheat/Crop | AS79: WO | AT79: Wheat-Crop-Fallow | AU79: yes | AV79: No | AW79: Wheat-Crop-Fallow | AX79: No | AY79: No | BK79: CC | BM79: Fallow | BN79: 4 | BO79: 4 | BQ79: Split-split-plot RCBD | BV79: Subplot, Cover | CH79: 1.49 | CI79: 1.4 | CM79: =8.8*100/1000 -> 0.88 | CN79: 0.99 | CR79: 9.9 | CS79: 11.5 | CV79: SOC, Units in Mg per Ha available | DA79: SOC (Mg per Ha) | GP79: Not reported | JU79: Geometric mean Diameter of dry aggregates, water-stable, available
A80: 79 | B80: SoilHealthDB_V2_Jian et al | C80: 5 | D80: 5-1 | E80: Blanco-Canqui | G80: Humberto | H80: 2013 | I80: 2012 | J80: Soil and Water Management and Conservation | K80: Garden City, KS | L80: USA | M80: 37.97 | N80: -100.87 | O80: 865.6 | R80: 308 | S80: 489 | U80: 5 | V80: 5 | Y80: 2007-2012 | Z80: 0-to-7.5 | AA80: 7.5 | AD80: 1.49 | AH80: Silt loam | AM80: Aridic Haplustolls | AN80: Pea_Spring | AO80: yes | AQ80: Legume | AR80: Winter_wheat/Crop | AS80: WO | AT80: Wheat-Crop-Fallow | AU80: yes | AV80: No | AW80: Wheat-Crop-Fallow | AX80: No | AY80: No | BK80: CC | BM80: Fallow | BN80: 4 | BO80: 4 | BQ80: Split-split-plot RCBD | BV80: Subplot, Hayed | CH80: 1.49 | CI80: 1.4 | CM80: =8.8*100/1000 -> 0.88 | CN80: 1.06 | CR80: 9.9 | CS80: 12.1 | CV80: SOC, Units in Mg per Ha available | DA80: SOC (Mg per Ha) | GP80: Not reported | JU80: Geometric mean Diameter of dry aggregates, water-stable, available
A81: 80 | B81: SoilHealthDB_V2_Jian et al | C81: 6 | D81: 6-1 | E81: Bloszies | G81: Sean Alaric | H81: 2016 | I81: 2012 | J81: PhD Dissertation | L81: USA | M81: 35.38 | N81: -77.99 | O81: 32.7 | U81: 1 | V81: 2 | Y81: 2012-2013 | Z81: 0-to-15 | AA81: 15 | AE81: =(21.7+27.4)/2 -> 24.55 | AF81: =(60+63.7)/2 -> 61.85 | AH81: Loamy sand | AM81: Wickham | AN81: Crimson_clover | AO81: yes | AQ81: Legume | AR81: Soybean | AS81: Soybean | AU81: Not reported | AV81: No | AX81: No | AZ81: Conventional disk tillage | BA81: Conventional disk tillage | BB81: CT | BC81: CT | BD81: No | BK81: CC | BM81: No cover crop | BN81: 6 | BO81: 6 | BQ81: Split-split-plot RCBD | BS81: =9.66*1000 -> 9660 | EK81: 5.02 | EL81: 3.22 | EO81: Aggregate mean weight diameter (mm) | GD81: 0.1616 | GE81: 0.1666 | GP81: Not reported | HX81: 501.83 | HY81: 441.12 | IB81: Potentially mineralizable C | JG81: 329.48 | JH81: 341.32 | JK81: Chloroform fumigation±extraction method
A82: 81 | B82: SoilHealthDB_V2_Jian et al | C82: 6 | D82: 6-2 | E82: Bloszies | G82: Sean Alaric | H82: 2016 | I82: 2012 | J82: PhD Dissertation | L82: USA | M82: 35.38 | N82: -77.99 | O82: 32.7 | U82: 1 | V82: 2 | Y82: 2012-2013 | Z82: 0-to-15 | AA82: 15 | AE82: =(21.7+27.4)/2 -> 24.55 | AF82: =(60+63.7)/2 -> 61.85 | AH82: Loamy sand | AM82: Wickham | AN82: Vetch | AO82: yes | AQ82: Legume | AR82: Soybean | AS82: Soybean | AU82: Not reported | AV82: No | AX82: No | AZ82: Conventional disk tillage | BA82: Conventional disk tillage | BB82: CT | BC82: CT | BD82: No | BK82: CC | BM82: No cover crop | BN82: 6 | BO82: 6 | BQ82: Split-split-plot RCBD | BS82: =8.83*1000 -> 8830 | EK82: 5.02 | EL82: 3.64 | EO82: Aggregate mean weight diameter (mm) | GD82: 0.1618 | GE82: 0.1472 | GP82: Not reported | HX82: 501.83 | HY82: 477.97 | IB82: Potentially mineralizable C | JG82: 329.48 | JH82: 337.39 | JK82: Chloroform fumigation±extraction method
A83: 82 | B83: SoilHealthDB_V2_Jian et al | C83: 6 | D83: 6-1 | E83: Bloszies | G83: Sean Alaric | H83: 2016 | I83: 2013 | J83: PhD Dissertation | L83: USA | M83: 35.38 | N83: -77.99 | O83: 32.7 | U83: 2 | V83: 2 | Y83: 2012-2013 | Z83: 0-to-15 | AA83: 15 | AE83: =(21.7+27.4)/2 -> 24.55 | AF83: =(60+63.7)/2 -> 61.85 | AH83: Loamy sand | AM83: Wickham | AN83: Crimson_clover | AO83: yes | AQ83: Legume | AR83: Soybean | AS83: Soybean | AU83: Not reported | AV83: No | AX83: No | AZ83: Conventional disk tillage | BA83: Conventional disk tillage | BB83: CT | BC83: CT | BD83: No | BK83: CC | BM83: No cover crop | BN83: 6 | BO83: 6 | BQ83: Split-split-plot RCBD | BS83: =4.42*1000 -> 4420 | EK83: 2.99 | EL83: 2.33 | EO83: Aggregate mean weight diameter (mm) | GD83: 0.1163 | GE83: 0.1176 | GP83: Not reported | HX83: 501.83 | HY83: 441.12 | IB83: Potentially mineralizable C | JG83: 329.48 | JH83: 341.32 | JK83: Chloroform fumigation±extraction method
A84: 83 | B84: SoilHealthDB_V2_Jian et al | C84: 6 | D84: 6-2 | E84: Bloszies | G84: Sean Alaric | H84: 2016 | I84: 2013 | J84: PhD Dissertation | L84: USA | M84: 35.38 | N84: -77.99 | O84: 32.7 | U84: 2 | V84: 2 | Y84: 2012-2013 | Z84: 0-to-15 | AA84: 15 | AE84: =(21.7+27.4)/2 -> 24.55 | AF84: =(60+63.7)/2 -> 61.85 | AH84: Loamy sand | AM84: Wickham | AN84: Vetch | AO84: yes | AQ84: Legume | AR84: Soybean | AS84: Soybean | AU84: Not reported | AV84: No | AX84: No | AZ84: Conventional disk tillage | BA84: Conventional disk tillage | BB84: CT | BC84: CT | BD84: No | BK84: CC | BM84: No cover crop | BN84: 6 | BO84: 6 | BQ84: Split-split-plot RCBD | BS84: =5.46*1000 -> 5460 | EK84: 2.99 | EL84: 3.17 | EO84: Aggregate mean weight diameter (mm) | GD84: 0.1163 | GE84: 0.1262 | GP84: Not reported | HX84: 501.83 | HY84: 447.97 | IB84: Potentially mineralizable C | JG84: 329.48 | JH84: 337.39 | JK84: Chloroform fumigation±extraction method
A85: 84 | B85: SoilHealthDB_V2_Jian et al | C85: 7 | D85: 7-1 | E85: Bottomley | G85: P.J. | H85: 1999 | I85: 1995 | J85: Soil Biology and Biochemistry | K85: Aurora, OR | L85: USA | M85: 45.23 | N85: -122.76 | O85: 48.4 | S85: 1040 | T85: Mediterranean | U85: 2 | V85: 7 | Y85: 1989-1995 | Z85: 0-to-20 | AA85: 20 | AE85: =313/(313+540+147)*100 -> 31.3 | AF85: =540/(313+540+147)*100 -> 54 | AH85: Silt loam | AI85: 6.3 | AJ85: =18/1000*100 -> 1.8 | AL85: 60 | AM85: Pachic Ultic Argixeroll | AN85: Rye | AO85: yes | AQ85: Rye | AR85: Sweetcorn | AS85: CV | AT85: Sweet corn ratation with broccoli | AU85: yes | AV85: No | AW85: Sweet corn ratation with broccoli | AX85: No | AY85: No | BK85: CC | BM85: Fallow | BN85: 4 | BO85: 4 | BQ85: RCBD | GP85: Not reported | IR85: =970/22.7273 -> 42.679949 | IS85: =610/22.7273 -> 26.839968 | IV85: =400/22.7273 -> 17.599979 | JG85: 140 | JH85: 204 | JK85: 58
A86: 85 | B86: SoilHealthDB_V2_Jian et al | C86: 7 | D86: 7-2 | E86: Bottomley | G86: P.J. | H86: 1999 | I86: 1995 | J86: Soil Biology and Biochemistry | K86: Aurora, OR | L86: USA | M86: 45.23 | N86: -122.76 | O86: 48.4 | S86: 1040 | T86: Mediterranean | U86: 2 | V86: 7 | Y86: 1989-1995 | Z86: 20-to-40 | AA86: 20 | AE86: =313/(313+540+147)*100 -> 31.3 | AF86: =540/(313+540+147)*100 -> 54 | AH86: Silt loam | AJ86: =18/1000*100 -> 1.8 | AM86: Pachic Ultic Argixeroll | AN86: Rye | AO86: yes | AQ86: Rye | AR86: Sweetcorn | AS86: CV | AT86: Sweet corn ratation with broccoli | AU86: yes | AV86: No | AW86: Sweet corn ratation with broccoli | AX86: No | AY86: No | BK86: CC | BM86: Fallow | BN86: 4 | BO86: 4 | BQ86: RCBD | GP86: Not reported | IR86: =276/22.7273 -> 12.143985 | IS86: =260/22.7273 -> 11.439986 | IV86: =116/22.7273 -> 5.1039939 | JG86: 148 | JH86: 135 | JK86: 62
A87: 86 | B87: SoilHealthDB_V2_Jian et al | C87: 7 | D87: 7-3 | E87: Bottomley | G87: P.J. | H87: 1999 | I87: 1995 | J87: Soil Biology and Biochemistry | K87: Aurora, OR | L87: USA | M87: 45.23 | N87: -122.76 | O87: 48.4 | S87: 1040 | T87: Mediterranean | U87: 2 | V87: 7 | Y87: 1989-1995 | Z87: 40-to-60 | AA87: 20 | AE87: =313/(313+540+147)*100 -> 31.3 | AF87: =540/(313+540+147)*100 -> 54 | AH87: Silt loam | AI87: 6.3 | AJ87: =9.4/1000*100 -> 0.94 | AL87: 7 | AM87: Pachic Ultic Argixeroll | AN87: Rye | AO87: yes | AQ87: Rye | AR87: Sweetcorn | AS87: CV | AT87: Sweet corn ratation with broccoli | AU87: yes | AV87: No | AW87: Sweet corn ratation with broccoli | AX87: No | AY87: No | BK87: CC | BM87: Fallow | BN87: 4 | BO87: 4 | BQ87: RCBD | GP87: Not reported | IR87: =352/22.7273 -> 15.487981 | IS87: =90/22.7273 -> 3.9599952 | IV87: =144/22.7273 -> 6.3359924 | JG87: 86 | JH87: 45 | JK87: 35
A88: 87 | B88: SoilHealthDB_V2_Jian et al | C88: 7 | D88: 7-4 | E88: Bottomley | G88: P.J. | H88: 1999 | I88: 1995 | J88: Soil Biology and Biochemistry | K88: Aurora, OR | L88: USA | M88: 45.23 | N88: -122.76 | O88: 48.4 | S88: 1040 | T88: Mediterranean | U88: 2 | V88: 7 | Y88: 1989-1995 | Z88: 60-to-80 | AA88: 20 | AE88: =313/(313+540+147)*100 -> 31.3 | AF88: =540/(313+540+147)*100 -> 54 | AH88: Silt loam | AJ88: =6.5/1000*100 -> 0.65 | AM88: Pachic Ultic Argixeroll | AN88: Rye | AO88: yes | AQ88: Rye | AR88: Sweetcorn | AS88: CV | AT88: Sweet corn ratation with broccoli | AU88: yes | AV88: No | AW88: Sweet corn ratation with broccoli | AX88: No | AY88: No | BK88: CC | BM88: Fallow | BN88: 4 | BO88: 4 | BQ88: RCBD | GP88: Not reported | IR88: =60/22.7273 -> 2.6399968 | IS88: =150/22.7273 -> 6.5999921 | IV88: =26/22.7273 -> 1.1439986 | JG88: 28 | JH88: 29 | JK88: 12
A89: 88 | B89: SoilHealthDB_V2_Jian et al | C89: 7 | D89: 7-5 | E89: Bottomley | G89: P.J. | H89: 1999 | I89: 1995 | J89: Soil Biology and Biochemistry | K89: Aurora, OR | L89: USA | M89: 45.23 | N89: -122.76 | O89: 48.4 | S89: 1040 | T89: Mediterranean | U89: 2 | V89: 7 | Y89: 1989-1995 | Z89: 80-to-100 | AA89: 20 | AE89: =313/(313+540+147)*100 -> 31.3 | AF89: =540/(313+540+147)*100 -> 54 | AH89: Silt loam | AI89: 6.2 | AJ89: =4.7/1000*100 -> 0.47 | AL89: 0.7 | AM89: Pachic Ultic Argixeroll | AN89: Rye | AO89: yes | AQ89: Rye | AR89: Sweetcorn | AS89: CV | AT89: Sweet corn ratation with broccoli | AU89: yes | AV89: No | AW89: Sweet corn ratation with broccoli | AX89: No | AY89: No | BK89: CC | BM89: Fallow | BN89: 4 | BO89: 4 | BQ89: RCBD | GP89: Not reported | IR89: =80/22.7273 -> 3.5199958 | IS89: =70/22.7273 -> 3.0799963 | IV89: =33/22.7273 -> 1.4519983
A90: 89 | B90: SoilHealthDB_V2_Jian et al | C90: 8 | D90: 8-1 | E90: Brainard | G90: D.C. | H90: 2016 | I90: 2010 | J90: Agriculture, Ecosystems and Environment | K90: Benton Harbor MI USA | L90: USA | M90: =42+4/60 -> 42.066667 | N90: =-86-21/60 -> -86.35 | O90: 205 | U90: 1 | V90: 3 | Y90: 2009-2011, May | Z90: Not-available | AA90: Not-available | AH90: Sand | AM90: Udipsamment | AN90: Rye | AO90: yes | AQ90: Rye | AR90: Snap_bean/Sweetcorn | AS90: CV | AT90: Rotation with sweet corn | AU90: yes | AV90: No | AW90: Rotation with sweet corn | AX90: No | AY90: No | AZ90: Hiniker1 Model 6000 two-row strip-tiller tillage | BA90: Hiniker1 Model 6000 two-row strip-tiller tillage | BB90: CT | BC90: CT | BD90: No | BH90: NPK fertilization | BI90: Yes | BK90: CC | BM90: Fallow | BN90: 4 | BO90: 4 | BQ90: Split-split-plot RCBD | BS90: =528.88*10 -> 5288.8 | CB90: =5.09*1000 -> 5090 | CC90: =4.94*1000 -> 4940 | GN90: =(40+13+41+3+326)/5 -> 84.6 | GO90: =(9+4+40+2+127)/5 -> 36.4 | GP90: yes | GS90: Weed density, averaged from 5 | GY90: =(0+0.77+1.87+3.67)/4 -> 1.5775 | GZ90: =(0+3.17+4.6+6.17)/4 -> 3.485 | HC90: pests | JU90: Pest , natural enemies as pests control
A91: 90 | B91: SoilHealthDB_V2_Jian et al | C91: 8 | D91: 8-2 | E91: Brainard | G91: D.C. | H91: 2016 | I91: 2011 | J91: Agriculture, Ecosystems and Environment | K91: Benton Harbor MI USA | L91: USA | M91: =42+4/60 -> 42.066667 | N91: =-86-21/60 -> -86.35 | O91: 205 | U91: 2 | V91: 3 | Y91: 2009-2011, May | Z91: Not-available | AA91: Not-available | AH91: Sand | AM91: Udipsamment | AN91: Rye | AO91: yes | AQ91: Rye | AR91: Snap_bean/Sweetcorn | AS91: CV | AT91: Rotation with sweet corn | AU91: yes | AV91: No | AW91: Rotation with sweet corn | AX91: No | AY91: No | AZ91: Hiniker1 Model 6000 two-row strip-tiller tillage | BA91: Hiniker1 Model 6000 two-row strip-tiller tillage | BB91: CT | BC91: CT | BD91: No | BH91: NPK fertilization | BI91: Yes | BK91: CC | BM91: Fallow | BN91: 4 | BO91: 4 | BQ91: Split-split-plot RCBD | BS91: =372.96*10 -> 3729.6 | CB91: =5.31*1000 -> 5310 | CC91: =5.01*1000 -> 5010 | GN91: =(24+0+5+391+16)/5 -> 87.2 | GO91: =(2+0+15+260+4)/5 -> 56.2 | GP91: yes | GS91: Weed density, averaged from 5 | GY91: =(8.74+0.7+2.32+7.31)/4 -> 4.7675 | GZ91: =(8.36+0.59+2.43+6.66)/4 -> 4.51 | HC91: pests | JU91: Pest , natural enemies as pests control
A92: 91 | B92: SoilHealthDB_V2_Jian et al | C92: 8 | D92: 8-1 | E92: Brainard | G92: D.C. | H92: 2016 | I92: 2010 | J92: Agriculture, Ecosystems and Environment | K92: Benton Harbor MI USA | L92: USA | M92: =42+4/60 -> 42.066667 | N92: =-86-21/60 -> -86.35 | O92: 205 | U92: 1 | V92: 3 | Y92: 2009-2011, May | Z92: Not-available | AA92: Not-available | AH92: Sand | AM92: Udipsamment | AN92: Rye | AO92: yes | AQ92: Rye | AR92: Snap_bean/Sweetcorn | AS92: CV | AT92: Rotation with sweet corn | AU92: yes | AV92: No | AW92: Rotation with sweet corn | AX92: No | AY92: No | AZ92: Hiniker1 Model 6000 two-row strip-tiller tillage | BA92: Hiniker1 Model 6000 two-row strip-tiller tillage | BB92: CT | BC92: CT | BD92: No | BH92: NPK fertilization | BI92: Yes | BK92: CC | BM92: Fallow | BN92: 4 | BO92: 4 | BQ92: Split-split-plot RCBD | BS92: =528.88*10 -> 5288.8 | GP92: Not reported | GY92: =1/((3.83+1.45+0.51+0.06+1.54)/5) -> 0.67658999 | GZ92: =1/((7.05+0.33+0.22+1.39+0.72)/5) -> 0.51493306 | HC92: 1/Natural enimies (average of 5) | JU92: Pest , natural enemies as pests control
A93: 92 | B93: SoilHealthDB_V2_Jian et al | C93: 8 | D93: 8-2 | E93: Brainard | G93: D.C. | H93: 2016 | I93: 2011 | J93: Agriculture, Ecosystems and Environment | K93: Benton Harbor MI USA | L93: USA | M93: =42+4/60 -> 42.066667 | N93: =-86-21/60 -> -86.35 | O93: 205 | U93: 2 | V93: 3 | Y93: 2009-2011, May | Z93: Not-available | AA93: Not-available | AH93: Sand | AM93: Udipsamment | AN93: Rye | AO93: yes | AQ93: Rye | AR93: Snap_bean/Sweetcorn | AS93: CV | AT93: Rotation with sweet corn | AU93: yes | AV93: No | AW93: Rotation with sweet corn | AX93: No | AY93: No | AZ93: Hiniker1 Model 6000 two-row strip-tiller tillage | BA93: Hiniker1 Model 6000 two-row strip-tiller tillage | BB93: CT | BC93: CT | BD93: No | BH93: NPK fertilization | BI93: Yes | BK93: CC | BM93: Fallow | BN93: 4 | BO93: 4 | BQ93: Split-split-plot RCBD | BS93: =372.96*10 -> 3729.6 | GP93: Not reported | GY93: =1/((0.7+0.05+0.2+0.02+0.21)/5) -> 4.2372881 | GZ93: =1/((0.71+0.16+0.07+0.02+0.13)/5) -> 4.587156 | HC93: 1/Natural enimies (average of 5) | JU93: Pest , natural enemies as pests control
A94: 93 | B94: SoilHealthDB_V2_Jian et al | C94: 9 | D94: 9-1 | E94: Bruce | G94: R.R. | H94: 1992 | I94: 1985 | J94: Soil Science Society of America Journal | K94: Watkinsville, GA | L94: USA | M94: =33+54/60 -> 33.9 | N94: =-82-24/60 -> -82.4 | O94: 130.1 | U94: 3 | V94: 5 | Y94: 1983-1987, March | Z94: 0-to-1.5 | AA94: 1.5 | AE94: =54.1/(54.1+14.6+5.8)*100 -> 72.61745 | AF94: =14.6/(54.1+14.6+5.8)*100 -> 19.597315 | AH94: Clay | AM94: Kanhapludults | AN94: Crimson_clover | AO94: yes | AQ94: Legume | AR94: Soybean | AS94: Soybean | AU94: Not reported | AV94: No | AX94: No | AZ94: Disk-harrowed seedbed | BA94: No-tillage | BB94: CT | BC94: NT | BD94: Yes | BK94: CC-NT | BM94: Fallow | BN94: 3 | BO94: 3 | BV94: E1, slightly erosion | EK94: =0.61*1000 -> 610 | EL94: =0.87*1000 -> 870 | EO94: g/kg | EZ94: =(26.7+29.5)/2 -> 28.1 | FA94: =(51.3+50.7)/2 -> 51 | FD94: infiltration defined as Rate (%) of rainfull | GP94: Not reported
A95: 94 | B95: SoilHealthDB_V2_Jian et al | C95: 9 | D95: 9-2 | E95: Bruce | G95: R.R. | H95: 1992 | I95: 1985 | J95: Soil Science Society of America Journal | K95: Watkinsville, GA | L95: USA | M95: =33+54/60 -> 33.9 | N95: =-82-24/60 -> -82.4 | O95: 130.1 | U95: 3 | V95: 5 | Y95: 1983-1987, March | Z95: 0-to-1.5 | AA95: 1.5 | AE95: =47/(47+20.4+10.7)*100 -> 60.179257 | AF95: =20.4/(47+20.4+10.7)*100 -> 26.120359 | AH95: Clay | AM95: Kanhapludults | AN95: Crimson_clover | AO95: yes | AQ95: Legume | AR95: Soybean | AS95: Soybean | AU95: Not reported | AV95: No | AX95: No | AZ95: Disk-harrowed seedbed | BA95: No-tillage | BB95: CT | BC95: NT | BD95: Yes | BK95: CC-NT | BM95: Fallow | BN95: 3 | BO95: 3 | BV95: E2, Moderately erosion | EK95: =0.59*1000 -> 590 | EL95: =0.88*1000 -> 880 | EO95: g/kg | EZ95: =(32.9+20.5)/2 -> 26.7 | FA95: =(51.8+46.4)/2 -> 49.1 | FD95: infiltration defined as Rate (%) of rainfull | GP95: Not reported
A96: 95 | B96: SoilHealthDB_V2_Jian et al | C96: 9 | D96: 9-3 | E96: Bruce | G96: R.R. | H96: 1992 | I96: 1985 | J96: Soil Science Society of America Journal | K96: Watkinsville, GA | L96: USA | M96: =33+54/60 -> 33.9 | N96: =-82-24/60 -> -82.4 | O96: 130.1 | U96: 3 | V96: 5 | Y96: 1983-1987, March | Z96: 0-to-1.5 | AA96: 1.5 | AE96: =42.5/(42.5+21.3+19)*100 -> 51.328502 | AF96: =21.3/(42.5+21.3+19)*100 -> 25.724638 | AH96: Clay | AM96: Kanhapludults | AN96: Crimson_clover | AO96: yes | AQ96: Legume | AR96: Soybean | AS96: Soybean | AU96: Not reported | AV96: No | AX96: No | AZ96: Disk-harrowed seedbed | BA96: No-tillage | BB96: CT | BC96: NT | BD96: Yes | BK96: CC-NT | BM96: Fallow | BN96: 3 | BO96: 3 | BV96: E3, Severely erosion | EK96: =0.65*1000 -> 650 | EL96: =0.91*1000 -> 910 | EO96: g/kg | EZ96: =(35.9+20.2)/2 -> 28.05 | FA96: =(46+41.6)/2 -> 43.8 | FD96: infiltration defined as Rate (%) of rainfull | GP96: Not reported
A97: 96 | B97: SoilHealthDB_V2_Jian et al | C97: 9 | D97: 9-1 | E97: Bruce | G97: R.R. | H97: 1992 | I97: 1985 | J97: Soil Science Society of America Journal | K97: Watkinsville, GA | L97: USA | M97: =33+54/60 -> 33.9 | N97: =-82-24/60 -> -82.4 | O97: 130.1 | U97: 3 | V97: 5 | Y97: 1983-1987, March | Z97: 0-to-1.5 | AA97: 1.5 | AE97: =54.1/(54.1+14.6+5.8)*100 -> 72.61745 | AF97: =14.6/(54.1+14.6+5.8)*100 -> 19.597315 | AH97: Clay | AM97: Kanhapludults | AN97: Crimson_clover | AO97: yes | AQ97: Legume | AR97: Sorghum | AS97: Sorghum | AU97: Not reported | AV97: No | AX97: No | AZ97: Disk-harrowed seedbed | BA97: No-tillage | BB97: CT | BC97: NT | BD97: Yes | BK97: CC-NT | BM97: Fallow | BN97: 3 | BO97: 3 | BV97: E1, slightly erosion | EK97: =0.5*1000 -> 500 | EL97: =0.87*1000 -> 870 | EO97: g/kg | EZ97: =(33+25.7)/2 -> 29.35 | FA97: =(51.3+50.7)/2 -> 51 | FD97: infiltration defined as Rate (%) of rainfull | GP97: Not reported
A98: 97 | B98: SoilHealthDB_V2_Jian et al | C98: 9 | D98: 9-2 | E98: Bruce | G98: R.R. | H98: 1992 | I98: 1985 | J98: Soil Science Society of America Journal | K98: Watkinsville, GA | L98: USA | M98: =33+54/60 -> 33.9 | N98: =-82-24/60 -> -82.4 | O98: 130.1 | U98: 3 | V98: 5 | Y98: 1983-1987, March | Z98: 0-to-1.5 | AA98: 1.5 | AE98: =47/(47+20.4+10.7)*100 -> 60.179257 | AF98: =20.4/(47+20.4+10.7)*100 -> 26.120359 | AH98: Clay | AM98: Kanhapludults | AN98: Crimson_clover | AO98: yes | AQ98: Legume | AR98: Sorghum | AS98: Sorghum | AU98: Not reported | AV98: No | AX98: No | AZ98: Disk-harrowed seedbed | BA98: No-tillage | BB98: CT | BC98: NT | BD98: Yes | BK98: CC-NT | BM98: Fallow | BN98: 3 | BO98: 3 | BV98: E2, Moderately erosion | EK98: =0.59*1000 -> 590 | EL98: =0.88*1000 -> 880 | EO98: g/kg | EZ98: =(38.6+20.1)/2 -> 29.35 | FA98: =(51.8+46.4)/2 -> 49.1 | FD98: infiltration defined as Rate (%) of rainfull | GP98: Not reported
A99: 98 | B99: SoilHealthDB_V2_Jian et al | C99: 9 | D99: 9-3 | E99: Bruce | G99: R.R. | H99: 1992 | I99: 1985 | J99: Soil Science Society of America Journal | K99: Watkinsville, GA | L99: USA | M99: =33+54/60 -> 33.9 | N99: =-82-24/60 -> -82.4 | O99: 130.1 | U99: 3 | V99: 5 | Y99: 1983-1987, March | Z99: 0-to-1.5 | AA99: 1.5 | AE99: =42.5/(42.5+21.3+19)*100 -> 51.328502 | AF99: =21.3/(42.5+21.3+19)*100 -> 25.724638 | AH99: Clay | AM99: Kanhapludults | AN99: Crimson_clover | AO99: yes | AQ99: Legume | AR99: Sorghum | AS99: Sorghum | AU99: Not reported | AV99: No | AX99: No | AZ99: Disk-harrowed seedbed | BA99: No-tillage | BB99: CT | BC99: NT | BD99: Yes | BK99: CC-NT | BM99: Fallow | BN99: 3 | BO99: 3 | BV99: E3, Severely erosion | EK99: =0.64*1000 -> 640 | EL99: =0.91*1000 -> 910 | EO99: g/kg | EZ99: =(34.5+21)/2 -> 27.75 | FA99: =(46+41.6)/2 -> 43.8 | FD99: infiltration defined as Rate (%) of rainfull | GP99: Not reported
A100: 99 | B100: SoilHealthDB_V2_Jian et al | C100: 10 | D100: 10-1 | E100: Bulan | G100: Mary T. Saunders | H100: 2015 | I100: 2010 | J100: Weed Science | K100: University of Wisconsin West Madison Agricultural Research Station | L100: USA | M100: 43.065 | N100: -89.535 | O100: 331.7 | U100: 1 | V100: 2 | Y100: 2010-2011, July | Z100: 0-to-15 | AA100: 15 | AH100: Silt loam | AI100: 7.1 | AJ100: 2.9 | AM100: Kegonsa | AN100: Buckwheat | AO100: yes | AQ100: Grass | AR100: Vegetable | AS100: Vegetable | AU100: Not reported | AV100: No | AX100: No | AZ100: Conventional tillage | BA100: Conventional tillage | BB100: CT | BC100: CT | BD100: No | BK100: CC | BM100: Fallow | BN100: 4 | BO100: 4 | CB100: =(40+24.2)/2*1000 -> 32100 | CC100: =(31.5+25.7)/2*1000 -> 28600 | CG100: Weed-free and weedy aggregated | DB100: 11.22 | DC100: 8.83 | DF100: Nitrate-nitrogen in ppm | GN100: 2320 | GO100: 630 | GP100: yes
A101: 100 | B101: SoilHealthDB_V2_Jian et al | C101: 10 | D101: 10-1 | E101: Bulan | G101: Mary T. Saunders | H101: 2015 | I101: 2011 | J101: Weed Science | K101: University of Wisconsin West Madison Agricultural Research Station | L101: USA | M101: 43.065 | N101: -89.535 | O101: 331.7 | U101: 2 | V101: 2 | Y101: 2010-2011, August | Z101: 0-to-15 | AA101: 15 | AH101: Silt loam | AI101: 7.1 | AJ101: 2.9 | AM101: Kegonsa | AN101: Buckwheat | AO101: yes | AQ101: Grass | AR101: Vegetable | AS101: Vegetable | AU101: Not reported | AV101: No | AX101: No | AZ101: Conventional tillage | BA101: Conventional tillage | BB101: CT | BC101: CT | BD101: No | BK101: CC | BM101: Fallow | BN101: 4 | BO101: 4 | DB101: 17.41 | DC101: 15.03 | DF101: Nitrate-nitrogen in ppm | GN101: 1130 | GO101: 230 | GP101: yes
A102: 101 | B102: SoilHealthDB_V2_Jian et al | C102: 10 | D102: 10-1 | E102: Bulan | G102: Mary T. Saunders | H102: 2015 | I102: 2011 | J102: Weed Science | K102: University of Wisconsin Arlington Agricultural Research Station | L102: USA | M102: 43.314 | N102: -89.336 | O102: 326.5 | U102: 2 | V102: 2 | Y102: 2010-2011, September | Z102: 0-to-15 | AA102: 15 | AH102: Silt loam | AI102: 7.3 | AJ102: 4 | AM102: Kegonsa | AN102: Buckwheat | AO102: yes | AQ102: Grass | AR102: Vegetable | AS102: Vegetable | AU102: Not reported | AV102: No | AX102: No | AZ102: Conventional tillage | BA102: Conventional tillage | BB102: CT | BC102: CT | BD102: No | BK102: CC | BM102: Fallow | BN102: 4 | BO102: 4 | DB102: 27.1 | DC102: 18.3 | DF102: Nitrate-nitrogen in ppm | GN102: 610 | GO102: 60 | GP102: yes
A103: 102 | B103: SoilHealthDB_V2_Jian et al | C103: 10 | D103: 10-1 | E103: Bulan | G103: Mary T. Saunders | H103: 2015 | I103: 2010 | J103: Weed Science | K103: University of Wisconsin West Madison Agricultural Research Station | L103: USA | M103: 43.065 | N103: -89.535 | O103: 331.7 | U103: 1 | V103: 2 | Y103: 2010-2011, July | Z103: 0-to-15 | AA103: 15 | AH103: Silt loam | AI103: 7.1 | AJ103: 2.9 | AM103: Kegonsa | AN103: Tartary_Buckwheat | AO103: yes | AQ103: Grass | AR103: Vegetable | AS103: Vegetable | AU103: Not reported | AV103: No | AX103: No | AZ103: Conventional tillage | BA103: Conventional tillage | BB103: CT | BC103: CT | BD103: No | BK103: CC | BM103: Fallow | BN103: 4 | BO103: 4 | CB103: =(40+24.2)/2*1000 -> 32100 | CC103: =(42.1+29.8)/2*1000 -> 35950 | CG103: Weed-free and weedy aggregated | DB103: 11.22 | DC103: 9.34 | DF103: Nitrate-nitrogen in ppm | GN103: 2320 | GO103: 2040 | GP103: yes
A104: 103 | B104: SoilHealthDB_V2_Jian et al | C104: 10 | D104: 10-1 | E104: Bulan | G104: Mary T. Saunders | H104: 2015 | I104: 2011 | J104: Weed Science | K104: University of Wisconsin West Madison Agricultural Research Station | L104: USA | M104: 43.065 | N104: -89.535 | O104: 331.7 | U104: 2 | V104: 2 | Y104: 2010-2011, August | Z104: 0-to-15 | AA104: 15 | AH104: Silt loam | AI104: 7.1 | AJ104: 2.9 | AM104: Kegonsa | AN104: Tartary_Buckwheat | AO104: yes | AQ104: Grass | AR104: Vegetable | AS104: Vegetable | AU104: Not reported | AV104: No | AX104: No | AZ104: Conventional tillage | BA104: Conventional tillage | BB104: CT | BC104: CT | BD104: No | BK104: CC | BM104: Fallow | BN104: 4 | BO104: 4 | DB104: 17.41 | DC104: 15.54 | DF104: Nitrate-nitrogen in ppm | GN104: 1130 | GO104: 270 | GP104: yes
A105: 104 | B105: SoilHealthDB_V2_Jian et al | C105: 10 | D105: 10-1 | E105: Bulan | G105: Mary T. Saunders | H105: 2015 | I105: 2011 | J105: Weed Science | K105: University of Wisconsin Arlington Agricultural Research Station | L105: USA | M105: 43.314 | N105: -89.336 | O105: 326.5 | U105: 2 | V105: 2 | Y105: 2010-2011, September | Z105: 0-to-15 | AA105: 15 | AH105: Silt loam | AI105: 7.3 | AJ105: 4 | AM105: Kegonsa | AN105: Tartary_Buckwheat | AO105: yes | AQ105: Grass | AR105: Vegetable | AS105: Vegetable | AU105: Not reported | AV105: No | AX105: No | AZ105: Conventional tillage | BA105: Conventional tillage | BB105: CT | BC105: CT | BD105: No | BK105: CC | BM105: Fallow | BN105: 4 | BO105: 4 | DB105: 27.1 | DC105: 19.45 | DF105: Nitrate-nitrogen in ppm | GN105: 610 | GO105: 330 | GP105: yes
A106: 105 | B106: SoilHealthDB_V2_Jian et al | C106: 10 | D106: 10-2 | E106: Bulan | G106: Mary T. Saunders | H106: 2015 | I106: 2010 | J106: Weed Science | K106: University of Wisconsin West Madison Agricultural Research Station | L106: USA | M106: 43.065 | N106: -89.535 | O106: 331.7 | U106: 1 | V106: 2 | Y106: 2010-2011, July | Z106: 0-to-15 | AA106: 15 | AH106: Silt loam | AI106: 7.1 | AJ106: 2.9 | AM106: Kegonsa | AN106: Buckwheat | AO106: yes | AQ106: Grass | AR106: Vegetable | AS106: Vegetable | AU106: Not reported | AV106: No | AX106: No | AZ106: Conventional tillage | BA106: No-tillage | BB106: CT | BC106: NT | BD106: Yes | BK106: CC-NT | BM106: Fallow | BN106: 4 | BO106: 4 | CB106: =(40+24.2)/2*1000 -> 32100 | CC106: =(6.5+0.7+7.8+0)/4*1000 -> 3750 | CG106: Weed-free and weedy aggregated | DB106: 11.22 | DC106: 4.84 | DF106: Nitrate-nitrogen in ppm | GP106: Not reported
A107: 106 | B107: SoilHealthDB_V2_Jian et al | C107: 10 | D107: 10-2 | E107: Bulan | G107: Mary T. Saunders | H107: 2015 | I107: 2011 | J107: Weed Science | K107: University of Wisconsin West Madison Agricultural Research Station | L107: USA | M107: 43.065 | N107: -89.535 | O107: 331.7 | U107: 2 | V107: 2 | Y107: 2010-2011, August | Z107: 0-to-15 | AA107: 15 | AH107: Silt loam | AI107: 7.1 | AJ107: 2.9 | AM107: Kegonsa | AN107: Buckwheat | AO107: yes | AQ107: Grass | AR107: Vegetable | AS107: Vegetable | AU107: Not reported | AV107: No | AX107: No | AZ107: Conventional tillage | BA107: No-tillage | BB107: CT | BC107: NT | BD107: Yes | BK107: CC-NT | BM107: Fallow | BN107: 4 | BO107: 4 | DB107: 17.41 | DC107: 11.04 | DF107: Nitrate-nitrogen in ppm | GP107: Not reported
A108: 107 | B108: SoilHealthDB_V2_Jian et al | C108: 10 | D108: 10-2 | E108: Bulan | G108: Mary T. Saunders | H108: 2015 | I108: 2011 | J108: Weed Science | K108: University of Wisconsin Arlington Agricultural Research Station | L108: USA | M108: 43.314 | N108: -89.336 | O108: 326.5 | U108: 2 | V108: 2 | Y108: 2010-2011, September | Z108: 0-to-15 | AA108: 15 | AH108: Silt loam | AI108: 7.3 | AJ108: 4 | AM108: Kegonsa | AN108: Buckwheat | AO108: yes | AQ108: Grass | AR108: Vegetable | AS108: Vegetable | AU108: Not reported | AV108: No | AX108: No | AZ108: Conventional tillage | BA108: No-tillage | BB108: CT | BC108: NT | BD108: Yes | BK108: CC-NT | BM108: Fallow | BN108: 4 | BO108: 4 | DB108: 27.1 | DC108: 13.22 | DF108: Nitrate-nitrogen in ppm | GP108: Not reported
A109: 108 | B109: SoilHealthDB_V2_Jian et al | C109: 10 | D109: 10-2 | E109: Bulan | G109: Mary T. Saunders | H109: 2015 | I109: 2010 | J109: Weed Science | K109: University of Wisconsin West Madison Agricultural Research Station | L109: USA | M109: 43.065 | N109: -89.535 | O109: 331.7 | U109: 1 | V109: 2 | Y109: 2010-2011, July | Z109: 0-to-15 | AA109: 15 | AH109: Silt loam | AI109: 7.1 | AJ109: 2.9 | AM109: Kegonsa | AN109: Tartary_Buckwheat | AO109: yes | AQ109: Grass | AR109: Vegetable | AS109: Vegetable | AU109: Not reported | AV109: No | AX109: No | AZ109: Conventional tillage | BA109: No-tillage | BB109: CT | BC109: NT | BD109: Yes | BK109: CC-NT | BM109: Fallow | BN109: 4 | BO109: 4 | CB109: =(40+24.2)/2*1000 -> 32100 | CC109: =(2.1+0+13.4+8.1)/4*1000 -> 5900 | CG109: Weed-free and weedy aggregated | DB109: 11.22 | DC109: 5.04 | DF109: Nitrate-nitrogen in ppm | GP109: Not reported
A110: 109 | B110: SoilHealthDB_V2_Jian et al | C110: 10 | D110: 10-2 | E110: Bulan | G110: Mary T. Saunders | H110: 2015 | I110: 2011 | J110: Weed Science | K110: University of Wisconsin West Madison Agricultural Research Station | L110: USA | M110: 43.065 | N110: -89.535 | O110: 331.7 | U110: 2 | V110: 2 | Y110: 2010-2011, August | Z110: 0-to-15 | AA110: 15 | AH110: Silt loam | AI110: 7.1 | AJ110: 2.9 | AM110: Kegonsa | AN110: Tartary_Buckwheat | AO110: yes | AQ110: Grass | AR110: Vegetable | AS110: Vegetable | AU110: Not reported | AV110: No | AX110: No | AZ110: Conventional tillage | BA110: No-tillage | BB110: CT | BC110: NT | BD110: Yes | BK110: CC-NT | BM110: Fallow | BN110: 4 | BO110: 4 | DB110: 17.41 | DC110: 11.24 | DF110: Nitrate-nitrogen in ppm | GP110: Not reported
A111: 110 | B111: SoilHealthDB_V2_Jian et al | C111: 10 | D111: 10-2 | E111: Bulan | G111: Mary T. Saunders | H111: 2015 | I111: 2011 | J111: Weed Science | K111: University of Wisconsin Arlington Agricultural Research Station | L111: USA | M111: 43.314 | N111: -89.336 | O111: 326.5 | U111: 2 | V111: 2 | Y111: 2010-2011, September | Z111: 0-to-15 | AA111: 15 | AH111: Silt loam | AI111: 7.3 | AJ111: 4 | AM111: Kegonsa | AN111: Tartary_Buckwheat | AO111: yes | AQ111: Grass | AR111: Vegetable | AS111: Vegetable | AU111: Not reported | AV111: No | AX111: No | AZ111: Conventional tillage | BA111: No-tillage | BB111: CT | BC111: NT | BD111: Yes | BK111: CC-NT | BM111: Fallow | BN111: 4 | BO111: 4 | DB111: 27.1 | DC111: 11.8 | DF111: Nitrate-nitrogen in ppm | GP111: Not reported
A112: 111 | B112: SoilHealthDB_V2_Jian et al | C112: 11 | D112: 11-1 | E112: Buyer | G112: Jeffrey S. | H112: 2010 | I112: 2005 | J112: Soil Biology and Biochemistry | K112: Beltsville, Maryland | L112: USA | M112: 39.03 | N112: -76.91 | O112: 34.6 | U112: 1 | V112: 3 | Y112: 2005-2007, August | Z112: 0-to-15 | AA112: 15 | AE112: =(63+83)/2 -> 73 | AF112: =(7+27)/2 -> 17 | AH112: Sandy loam | AM112: Hapludults and Endoaquults | AN112: Rye | AO112: yes | AQ112: Rye | AR112: Tomato | AS112: Vegetable | AU112: Not reported | AV112: No | AX112: No | BE112: Lime and nutrients were applied | BF112: Yes | BG112: Yes | BH112: Lime and nutrients were applied | BI112: Yes | BJ112: No | BK112: CC | BM112: Bare | BN112: 4 | BO112: 4 | BQ112: RCBD | CB112: 56000 | CC112: 59600 | GP112: Not reported | HN112: =15.07*22.7273 -> 342.50041 | HO112: =19.33*22.7273 -> 439.31871 | HR112: PLFA was used as a measure of microbial biomass.
A113: 112 | B113: SoilHealthDB_V2_Jian et al | C113: 11 | D113: 11-1 | E113: Buyer | G113: Jeffrey S. | H113: 2010 | I113: 2005 | J113: Soil Biology and Biochemistry | K113: Beltsville, Maryland | L113: USA | M113: 39.03 | N113: -76.91 | O113: 34.6 | U113: 1 | V113: 3 | Y113: 2005-2007, August | Z113: 0-to-15 | AA113: 15 | AE113: =(63+83)/2 -> 73 | AF113: =(7+27)/2 -> 17 | AH113: Sandy loam | AM113: Hapludults and Endoaquults | AN113: Rye_roots | AO113: yes | AQ113: Rye | AR113: Tomato | AS113: Vegetable | AU113: Not reported | AV113: No | AX113: No | BE113: Lime and nutrients were applied | BF113: Yes | BG113: Yes | BH113: Lime and nutrients were applied | BI113: Yes | BJ113: No | BK113: CC | BM113: Bare | BN113: 4 | BO113: 4 | BQ113: RCBD | CB113: 56000 | CC113: 55100 | GP113: Not reported | HN113: =15.07*22.7273 -> 342.50041 | HO113: =18.39*22.7273 -> 417.95505 | HR113: PLFA was used as a measure of microbial biomass.
A114: 113 | B114: SoilHealthDB_V2_Jian et al | C114: 11 | D114: 11-1 | E114: Buyer | G114: Jeffrey S. | H114: 2010 | I114: 2005 | J114: Soil Biology and Biochemistry | K114: Beltsville, Maryland | L114: USA | M114: 39.03 | N114: -76.91 | O114: 34.6 | U114: 1 | V114: 3 | Y114: 2005-2007, August | Z114: 0-to-15 | AA114: 15 | AE114: =(63+83)/2 -> 73 | AF114: =(7+27)/2 -> 17 | AH114: Sandy loam | AM114: Hapludults and Endoaquults | AN114: Rye_shoots | AO114: yes | AQ114: Rye | AR114: Tomato | AS114: Vegetable | AU114: Not reported | AV114: No | AX114: No | BE114: Lime and nutrients were applied | BF114: Yes | BG114: Yes | BH114: Lime and nutrients were applied | BI114: Yes | BJ114: No | BK114: CC | BM114: Bare | BN114: 4 | BO114: 4 | BQ114: RCBD | CB114: 56000 | CC114: 57900 | GP114: Not reported | HN114: =15.07*22.7273 -> 342.50041 | HO114: =16.72*22.7273 -> 380.00046 | HR114: PLFA was used as a measure of microbial biomass.
A115: 114 | B115: SoilHealthDB_V2_Jian et al | C115: 11 | D115: 11-2 | E115: Buyer | G115: Jeffrey S. | H115: 2010 | I115: 2005 | J115: Soil Biology and Biochemistry | K115: Beltsville, Maryland | L115: USA | M115: 39.03 | N115: -76.91 | O115: 34.6 | U115: 1 | V115: 3 | Y115: 2005-2007, August | Z115: 0-to-15 | AA115: 15 | AE115: =(63+83)/2 -> 73 | AF115: =(7+27)/2 -> 17 | AH115: Sandy loam | AM115: Hapludults and Endoaquults | AN115: Vetch | AO115: yes | AQ115: Legume | AR115: Tomato | AS115: Vegetable | AU115: Not reported | AV115: No | AX115: No | BE115: Lime and nutrients were applied | BF115: Yes | BG115: Yes | BH115: Lime and nutrients were applied | BI115: Yes | BJ115: No | BK115: CC | BM115: Bare | BN115: 4 | BO115: 4 | BQ115: RCBD | CB115: 56000 | CC115: 56000 | GP115: Not reported | HN115: =15.07*22.7273 -> 342.50041 | HO115: =20.38*22.7273 -> 463.18237 | HR115: PLFA was used as a measure of microbial biomass.
A116: 115 | B116: SoilHealthDB_V2_Jian et al | C116: 11 | D116: 11-2 | E116: Buyer | G116: Jeffrey S. | H116: 2010 | I116: 2005 | J116: Soil Biology and Biochemistry | K116: Beltsville, Maryland | L116: USA | M116: 39.03 | N116: -76.91 | O116: 34.6 | U116: 1 | V116: 3 | Y116: 2005-2007, August | Z116: 0-to-15 | AA116: 15 | AE116: =(63+83)/2 -> 73 | AF116: =(7+27)/2 -> 17 | AH116: Sandy loam | AM116: Hapludults and Endoaquults | AN116: Vetch_roots | AO116: yes | AQ116: Legume | AR116: Tomato | AS116: Vegetable | AU116: Not reported | AV116: No | AX116: No | BE116: Lime and nutrients were applied | BF116: Yes | BG116: Yes | BH116: Lime and nutrients were applied | BI116: Yes | BJ116: No | BK116: CC | BM116: Bare | BN116: 4 | BO116: 4 | BQ116: RCBD | CB116: 56000 | CC116: 44400 | GP116: Not reported | HN116: =15.07*22.7273 -> 342.50041 | HO116: =19.04*22.7273 -> 432.72779 | HR116: PLFA was used as a measure of microbial biomass.
A117: 116 | B117: SoilHealthDB_V2_Jian et al | C117: 11 | D117: 11-2 | E117: Buyer | G117: Jeffrey S. | H117: 2010 | I117: 2005 | J117: Soil Biology and Biochemistry | K117: Beltsville, Maryland | L117: USA | M117: 39.03 | N117: -76.91 | O117: 34.6 | U117: 1 | V117: 3 | Y117: 2005-2007, August | Z117: 0-to-15 | AA117: 15 | AE117: =(63+83)/2 -> 73 | AF117: =(7+27)/2 -> 17 | AH117: Sandy loam | AM117: Hapludults and Endoaquults | AN117: Vetch_shoots | AO117: yes | AQ117: Legume | AR117: Tomato | AS117: Vegetable | AU117: Not reported | AV117: No | AX117: No | BE117: Lime and nutrients were applied | BF117: Yes | BG117: Yes | BH117: Lime and nutrients were applied | BI117: Yes | BJ117: No | BK117: CC | BM117: Bare | BN117: 4 | BO117: 4 | BQ117: RCBD | CB117: 56000 | CC117: 62300 | GP117: Not reported | HN117: =15.07*22.7273 -> 342.50041 | HO117: =17.39*22.7273 -> 395.22775 | HR117: PLFA was used as a measure of microbial biomass.
A118: 117 | B118: SoilHealthDB_V2_Jian et al | C118: 11 | D118: 11-1 | E118: Buyer | G118: Jeffrey S. | H118: 2010 | I118: 2006 | J118: Soil Biology and Biochemistry | K118: Beltsville, Maryland | L118: USA | M118: 39.03 | N118: -76.91 | O118: 34.6 | U118: 2 | V118: 3 | Y118: 2005-2007, August | Z118: 0-to-15 | AA118: 15 | AE118: =(63+83)/2 -> 73 | AF118: =(7+27)/2 -> 17 | AH118: Sandy loam | AM118: Hapludults and Endoaquults | AN118: Rye | AO118: yes | AQ118: Rye | AR118: Tomato | AS118: Vegetable | AU118: Not reported | AV118: No | AX118: No | BE118: Lime and nutrients were applied | BF118: Yes | BG118: Yes | BH118: Lime and nutrients were applied | BI118: Yes | BJ118: No | BK118: CC | BM118: Bare | BN118: 4 | BO118: 4 | BQ118: RCBD | CB118: 83900 | CC118: 80700 | GP118: Not reported
A119: 118 | B119: SoilHealthDB_V2_Jian et al | C119: 11 | D119: 11-1 | E119: Buyer | G119: Jeffrey S. | H119: 2010 | I119: 2006 | J119: Soil Biology and Biochemistry | K119: Beltsville, Maryland | L119: USA | M119: 39.03 | N119: -76.91 | O119: 34.6 | U119: 2 | V119: 3 | Y119: 2005-2007, August | Z119: 0-to-15 | AA119: 15 | AE119: =(63+83)/2 -> 73 | AF119: =(7+27)/2 -> 17 | AH119: Sandy loam | AM119: Hapludults and Endoaquults | AN119: Rye_roots | AO119: yes | AQ119: Rye | AR119: Tomato | AS119: Vegetable | AU119: Not reported | AV119: No | AX119: No | BE119: Lime and nutrients were applied | BF119: Yes | BG119: Yes | BH119: Lime and nutrients were applied | BI119: Yes | BJ119: No | BK119: CC | BM119: Bare | BN119: 4 | BO119: 4 | BQ119: RCBD | CB119: 83900 | CC119: 70900 | GP119: Not reported
A120: 119 | B120: SoilHealthDB_V2_Jian et al | C120: 11 | D120: 11-1 | E120: Buyer | G120: Jeffrey S. | H120: 2010 | I120: 2006 | J120: Soil Biology and Biochemistry | K120: Beltsville, Maryland | L120: USA | M120: 39.03 | N120: -76.91 | O120: 34.6 | U120: 2 | V120: 3 | Y120: 2005-2007, August | Z120: 0-to-15 | AA120: 15 | AE120: =(63+83)/2 -> 73 | AF120: =(7+27)/2 -> 17 | AH120: Sandy loam | AM120: Hapludults and Endoaquults | AN120: Rye_shoots | AO120: yes | AQ120: Rye | AR120: Tomato | AS120: Vegetable | AU120: Not reported | AV120: No | AX120: No | BE120: Lime and nutrients were applied | BF120: Yes | BG120: Yes | BH120: Lime and nutrients were applied | BI120: Yes | BJ120: No | BK120: CC | BM120: Bare | BN120: 4 | BO120: 4 | BQ120: RCBD | CB120: 83900 | CC120: 84100 | GP120: Not reported
A121: 120 | B121: SoilHealthDB_V2_Jian et al | C121: 11 | D121: 11-2 | E121: Buyer | G121: Jeffrey S. | H121: 2010 | I121: 2006 | J121: Soil Biology and Biochemistry | K121: Beltsville, Maryland | L121: USA | M121: 39.03 | N121: -76.91 | O121: 34.6 | U121: 2 | V121: 3 | Y121: 2005-2007, August | Z121: 0-to-15 | AA121: 15 | AE121: =(63+83)/2 -> 73 | AF121: =(7+27)/2 -> 17 | AH121: Sandy loam | AM121: Hapludults and Endoaquults | AN121: Vetch | AO121: yes | AQ121: Legume | AR121: Tomato | AS121: Vegetable | AU121: Not reported | AV121: No | AX121: No | BE121: Lime and nutrients were applied | BF121: Yes | BG121: Yes | BH121: Lime and nutrients were applied | BI121: Yes | BJ121: No | BK121: CC | BM121: Bare | BN121: 4 | BO121: 4 | BQ121: RCBD | CB121: 83900 | CC121: 82100 | GP121: Not reported
A122: 121 | B122: SoilHealthDB_V2_Jian et al | C122: 11 | D122: 11-2 | E122: Buyer | G122: Jeffrey S. | H122: 2010 | I122: 2006 | J122: Soil Biology and Biochemistry | K122: Beltsville, Maryland | L122: USA | M122: 39.03 | N122: -76.91 | O122: 34.6 | U122: 2 | V122: 3 | Y122: 2005-2007, August | Z122: 0-to-15 | AA122: 15 | AE122: =(63+83)/2 -> 73 | AF122: =(7+27)/2 -> 17 | AH122: Sandy loam | AM122: Hapludults and Endoaquults | AN122: Vetch_roots | AO122: yes | AQ122: Legume | AR122: Tomato | AS122: Vegetable | AU122: Not reported | AV122: No | AX122: No | BE122: Lime and nutrients were applied | BF122: Yes | BG122: Yes | BH122: Lime and nutrients were applied | BI122: Yes | BJ122: No | BK122: CC | BM122: Bare | BN122: 4 | BO122: 4 | BQ122: RCBD | CB122: 83900 | CC122: 59300 | GP122: Not reported
A123: 122 | B123: SoilHealthDB_V2_Jian et al | C123: 11 | D123: 11-2 | E123: Buyer | G123: Jeffrey S. | H123: 2010 | I123: 2006 | J123: Soil Biology and Biochemistry | K123: Beltsville, Maryland | L123: USA | M123: 39.03 | N123: -76.91 | O123: 34.6 | U123: 2 | V123: 3 | Y123: 2005-2007, August | Z123: 0-to-15 | AA123: 15 | AE123: =(63+83)/2 -> 73 | AF123: =(7+27)/2 -> 17 | AH123: Sandy loam | AM123: Hapludults and Endoaquults | AN123: Vetch_shoots | AO123: yes | AQ123: Legume | AR123: Tomato | AS123: Vegetable | AU123: Not reported | AV123: No | AX123: No | BE123: Lime and nutrients were applied | BF123: Yes | BG123: Yes | BH123: Lime and nutrients were applied | BI123: Yes | BJ123: No | BK123: CC | BM123: Bare | BN123: 4 | BO123: 4 | BQ123: RCBD | CB123: 83900 | CC123: 82600 | GP123: Not reported
A124: 123 | B124: SoilHealthDB_V2_Jian et al | C124: 11 | D124: 11-1 | E124: Buyer | G124: Jeffrey S. | H124: 2010 | I124: 2007 | J124: Soil Biology and Biochemistry | K124: Beltsville, Maryland | L124: USA | M124: 39.03 | N124: -76.91 | O124: 34.6 | U124: 3 | V124: 3 | Y124: 2005-2007, August | Z124: 0-to-15 | AA124: 15 | AE124: =(63+83)/2 -> 73 | AF124: =(7+27)/2 -> 17 | AH124: Sandy loam | AM124: Hapludults and Endoaquults | AN124: Rye | AO124: yes | AQ124: Rye | AR124: Tomato | AS124: Vegetable | AU124: Not reported | AV124: No | AX124: No | BE124: Lime and nutrients were applied | BF124: Yes | BG124: Yes | BH124: Lime and nutrients were applied | BI124: Yes | BJ124: No | BK124: CC | BM124: Bare | BN124: 4 | BO124: 4 | BQ124: RCBD | CB124: 88000 | CC124: 77800 | GP124: Not reported
A125: 124 | B125: SoilHealthDB_V2_Jian et al | C125: 11 | D125: 11-1 | E125: Buyer | G125: Jeffrey S. | H125: 2010 | I125: 2007 | J125: Soil Biology and Biochemistry | K125: Beltsville, Maryland | L125: USA | M125: 39.03 | N125: -76.91 | O125: 34.6 | U125: 3 | V125: 3 | Y125: 2005-2007, August | Z125: 0-to-15 | AA125: 15 | AE125: =(63+83)/2 -> 73 | AF125: =(7+27)/2 -> 17 | AH125: Sandy loam | AM125: Hapludults and Endoaquults | AN125: Rye_roots | AO125: yes | AQ125: Rye | AR125: Tomato | AS125: Vegetable | AU125: Not reported | AV125: No | AX125: No | BE125: Lime and nutrients were applied | BF125: Yes | BG125: Yes | BH125: Lime and nutrients were applied | BI125: Yes | BJ125: No | BK125: CC | BM125: Bare | BN125: 4 | BO125: 4 | BQ125: RCBD | CB125: 88000 | CC125: 65600 | GP125: Not reported
A126: 125 | B126: SoilHealthDB_V2_Jian et al | C126: 11 | D126: 11-1 | E126: Buyer | G126: Jeffrey S. | H126: 2010 | I126: 2007 | J126: Soil Biology and Biochemistry | K126: Beltsville, Maryland | L126: USA | M126: 39.03 | N126: -76.91 | O126: 34.6 | U126: 3 | V126: 3 | Y126: 2005-2007, August | Z126: 0-to-15 | AA126: 15 | AE126: =(63+83)/2 -> 73 | AF126: =(7+27)/2 -> 17 | AH126: Sandy loam | AM126: Hapludults and Endoaquults | AN126: Rye_shoots | AO126: yes | AQ126: Rye | AR126: Tomato | AS126: Vegetable | AU126: Not reported | AV126: No | AX126: No | BE126: Lime and nutrients were applied | BF126: Yes | BG126: Yes | BH126: Lime and nutrients were applied | BI126: Yes | BJ126: No | BK126: CC | BM126: Bare | BN126: 4 | BO126: 4 | BQ126: RCBD | CB126: 88000 | CC126: 82000 | GP126: Not reported
A127: 126 | B127: SoilHealthDB_V2_Jian et al | C127: 11 | D127: 11-2 | E127: Buyer | G127: Jeffrey S. | H127: 2010 | I127: 2007 | J127: Soil Biology and Biochemistry | K127: Beltsville, Maryland | L127: USA | M127: 39.03 | N127: -76.91 | O127: 34.6 | U127: 3 | V127: 3 | Y127: 2005-2007, August | Z127: 0-to-15 | AA127: 15 | AE127: =(63+83)/2 -> 73 | AF127: =(7+27)/2 -> 17 | AH127: Sandy loam | AM127: Hapludults and Endoaquults | AN127: Vetch | AO127: yes | AQ127: Legume | AR127: Tomato | AS127: Vegetable | AU127: Not reported | AV127: No | AX127: No | BE127: Lime and nutrients were applied | BF127: Yes | BG127: Yes | BH127: Lime and nutrients were applied | BI127: Yes | BJ127: No | BK127: CC | BM127: Bare | BN127: 4 | BO127: 4 | BQ127: RCBD | CB127: 88000 | CC127: 92200 | GP127: Not reported
A128: 127 | B128: SoilHealthDB_V2_Jian et al | C128: 11 | D128: 11-2 | E128: Buyer | G128: Jeffrey S. | H128: 2010 | I128: 2007 | J128: Soil Biology and Biochemistry | K128: Beltsville, Maryland | L128: USA | M128: 39.03 | N128: -76.91 | O128: 34.6 | U128: 3 | V128: 3 | Y128: 2005-2007, August | Z128: 0-to-15 | AA128: 15 | AE128: =(63+83)/2 -> 73 | AF128: =(7+27)/2 -> 17 | AH128: Sandy loam | AM128: Hapludults and Endoaquults | AN128: Vetch_roots | AO128: yes | AQ128: Legume | AR128: Tomato | AS128: Vegetable | AU128: Not reported | AV128: No | AX128: No | BE128: Lime and nutrients were applied | BF128: Yes | BG128: Yes | BH128: Lime and nutrients were applied | BI128: Yes | BJ128: No | BK128: CC | BM128: Bare | BN128: 4 | BO128: 4 | BQ128: RCBD | CB128: 88000 | CC128: 80200 | GP128: Not reported
A129: 128 | B129: SoilHealthDB_V2_Jian et al | C129: 11 | D129: 11-2 | E129: Buyer | G129: Jeffrey S. | H129: 2010 | I129: 2007 | J129: Soil Biology and Biochemistry | K129: Beltsville, Maryland | L129: USA | M129: 39.03 | N129: -76.91 | O129: 34.6 | U129: 3 | V129: 3 | Y129: 2005-2007, August | Z129: 0-to-15 | AA129: 15 | AE129: =(63+83)/2 -> 73 | AF129: =(7+27)/2 -> 17 | AH129: Sandy loam | AM129: Hapludults and Endoaquults | AN129: Vetch_shoots | AO129: yes | AQ129: Legume | AR129: Tomato | AS129: Vegetable | AU129: Not reported | AV129: No | AX129: No | BE129: Lime and nutrients were applied | BF129: Yes | BG129: Yes | BH129: Lime and nutrients were applied | BI129: Yes | BJ129: No | BK129: CC | BM129: Bare | BN129: 4 | BO129: 4 | BQ129: RCBD | CB129: 88000 | CC129: 93000 | GP129: Not reported
...

Sheet ReadMe
A1: Here, we compiled data from a set of soil health measurements collected across 41 countries around the world, named SoilHealthDB, which includes 5,241 data entries from 281 published studies. The SoilHealthDB includes 42 soil health indicators and 45 background indicators that describe factors such as climate, elevation, and soil type. A primary goal of SoilHealthDB is to enable the research community to perform comprehensive analyses, e.g., meta-analyses, of soil health changes related to cropland conservation management. The database also provides a common framework for sharing soil health, and the scientific research community is encouraged to contribute their own measurements. R code for quality checking and data processing are available at **RScripts**. All data (including meta data for clerification) were stored in 'SoilHealthDB_V1.xlsx'.
A2: SheetName | B2: Description
A3: Sheet1 | B3: Include all digitized data from 281 papers
A4: Explanation | B4: Explain each column in Sheet 1 in details
A5: ExperimentID | B5: Describe how Experiment ID were assigned according to site information
A6: Units convertion | B6: Meta information about unit convertion
A7: Rs Units Convertion | B7: Soil respiration unit convertion
A8: SoilClassficaton | B8: Different soil classification system in the world
A9: SoilDepth | B9: Diagram shows how soil sampling depth were grouped into 0-10cm, 0-20cm, 0-30cm, and >30cm
A10: CoverCropGroup | B10: Describe how cover crop grouped
A11: GrainCropGroup | B11: Describe how grain crop grouped
A12: TillageGroup | B12: Describe how tillage management grouped
A13: ConservationType | B13: Describe the type of conservation in the soil health database
... A16: Notes | B16: Other notes

Sheet ConservationType
A1: ID | B1: Conservation type | C1: Acronym | D1: Comments
A2: 1 | B2: Agriculture forest system | C2: AF
A3: 2 | B3: Cover crop | C3: CC
A4: 3 | B4: No tillage | C4: NT
A5: 4 | B5: Reduced tillage | C5: RT | D5: Deep tillage
A6: 5 | B6: Organic farm | C6: OF
A7: 6 | B7: Straw return, mulching | C7: SR
A8: 7 | B8: Stubble | C8: ST
A9: 8 | B9: Ridging | C9: RD | D9: 横坡垄作
A10: 9 | B10: Rotation | C10: RO
A11: 10 | B11: Plastic film mulching | C11: PF
A12: 11 | B12: Interplanting | C12: IN
A13: 12 | B13: Combination of two | C13: AF-CC
A14: 13 | B14: Organic farm with cover crop as green manure | C14: OF-CC
A15: 14 | B15: Organic farm with no tillage | C15: OF-NT

Sheet Explanation
A1: Meta information | B1: StudyID | C1: Paper's ID number
B2: ExperimentID | C2: Please see details in ExperimentID sheet
A3: Meta information | B3: Author_F | C3: Family author's Family name
B4: Author_G | C4: First author's Given name
B5: YearPublication | C5: Paper publication year
B6: SamplingYear | C6: Sampling year, should be earlier than publication year
B7: Journal | C7: Journal name of paper
B8: SiteInfor | C8: Site information | D8: Detail as possible
B9: Country | C9: Country name
B10: Latitude | C10: Latitude of site | D10: ° (degree)
B11: Longitude | C11: Longitude of site | D11: ° (degree)
B12: Elevation | C12: Elevation of site | D12: Units: m
B13: Tannual | C13: Annual average air temperature | D13: ℃
B14: MAT | C14: Mean annual air temperature within study period (1960-2017?) | D14: ℃
B15: Pannual | C15: Annual average precipitation | D15: Units: mm
B16: MAP | C16: Mean annual precipitation within study period (1960-2017?) | D16: Units: mm
B17: ClimateType | C17: Study site's climate type, can be obtain from climate koeppon | D17: A, B, C, D, E five first climate classification, 18? Second classification
B18: YearsAfterCoverCrop | C18: How many years cover crop applied before samples taken , e.g., experiment initiated at 1991, sample take at 1995, then fill with 5
B19: Duration | C19: How many years the whole experiment last for, e.g., experiement started at 1990 and end at 2000, duration is 11 years
B20: CC_planting_date | C20: Time that cover crops were planted
B21: CC_termination_date | C21: Time that cover crops were terminated
B22: Time_Comments | C22: Cover crop experiment period, also record comments about sampling time and others
B23: SoilDepthOfSample | C23: Soil sampling depth from top to bottom, formated as: top-to-botton, e.g., 10-to-20, and so on | D23: cm
B24: SamplingDepth | C24: Difference between bottom and top, e.g., 10-to-20, fill with 10, and so on
B25: CEC | C25: Cation exchangable capacity
B26: CEC_unit | C26: Unit of Cation exchange capacity
B27: SoilBD | C27: Bulk density
B28: SandPerc | C28: Percentage of sand
B29: SiltPerc | C29: Percentage of silt
B30: Texture | C30: Soil texture
B31: SoilpH | C31: Soil pH
B32: SoilTC | C32: Soil total C, this is the background soil carbon information, discriminate this column and OC_C, OC_T in the response | D32: Units: %
B33: SOC_NaturalVeg | C33: Soil organic carbon of near by natural vegetation land use, can be used as comparison as the potension carbon equlibrium status | D33: Units: %
B34: SoilKsat | C34: Soil Ksat | D34: cm/h if without explaination
B35: SoilFamily | C35: Soil family or soil group information, should be noted that there are many soil classification system in the word
B36: CoverCrop | C36: Cover crop type, some literature called catch crop, green manure
B37: CoverCropGroup | C37: Cover crop grouped by function or family, please see more details in the CoverCropGroup sheet | D37: See CoverCropGroup for more information
B38: GrainCrop | C38: Grain crop type, also called cash crop
B39: GrainCropGroup | C39: Grain crop grouped by function or family, please see more details in the GrainCropGroup sheet | D39: See GrainCropGroup for more information
B40: Landuse | C40: Landuse type
B41: Rotation_C | C41: Type of rotation/crop sequence for control
B42: Rotation_T | C42: Type of rotation/crop sequence for cover crop treatment
B43: Rotation_Diff | C43: Whether type of rotation/crop sequence differ between control and cover crop, yes or no
B44: Tillage_C | C44: Type of tillage for control
B45: Tillage_T | C45: Type of tillage for cover crop
B46: Tillage_Diff | C46: Whether type of tillage differ between control and cover crop, yes or no
B47: Fertilization_C | C47: Applied fertilization information for control
B48: Fertilization_T | C48: Applied fertilization information for cover crop
B49: Fert_Diff | C49: Whether control and cover crop applied different fertilizer level, yes or no
B50: ControlDescription | C50: Control description, winter fallow, summer fallow, no cover crop
B51: No_C | C51: Number of plot in control
... B54: ExperimentDesign | C54: CRD,RCBD, split-design etc.
B55: CCFreshBiomass | C55: Fresh biomass (and to be manure) of cover crop | D55: Units: kg/hm2 if without explaination in the comments
B56: CCDryBiomass | C56: Dry biomass (and to be manure) of cover crop | D56: Units: kg/hm2 if without explaination in the comments
B57: CNOfCoverCrop | C57: Carbon to nitrogen ratio from the dry biomass of cover crop (determine manure quality) | D57: Units: %
B58: CCTermination | C58: Method of killing cover crop
B59: Conservation_Type | C59: Including cover crop(CC), No-tillage(NT), organic farm(OGF), straw mulching etc.
B60: Conservation_Discription | C60: Description on conservation
B61: Others | C61: Other meta information need to make comments
A63: 1 | B63: BiomassCashCrop_C | C63: Biomass of cach crop (biomass of grain crop such as stem, leave, root, but not include yield) of control | D63: Units varied,unit is kg/hm2 if without explaination in the comments
B64: BiomassCashCrop_T | C64: Biomass of cach crop (biomass of grain crop such as stem, leave, root, but not include yield) of cover crop | D64: Units varied,unit is kg/hm2 if without explaination in the comments
B65: BiomassCashCrop_Comments | C65: Comments on biomass of cach crop (note that this biomass not include yield) | D65: Always make comments
A66: 2 | B66: yield_C | C66: Yield of grain(cash) crop from control | D66: Units: kg/hm2 if without explaination in the comments
A67: Target data | B67: yield_T | C67: Yield of grain(cash) crop from treatment | D67: Units: kg/hm2 if without explaination in the comments
B68: yield_Comments | C68: Comments on Yield of control | D68: Always make comments
A69: 3 | B69: BD_C | C69: Bulk density of control | D69: Always g/cm3
B70: BD_T | C70: Bulk density of treatment | D70: Always g/cm3
B71: BD_Comments | C71: Comments on bulk density of treatment | D71: Make comments if necessary
A72: 4 | B72: OC_C | C72: Organic carbon of control (mean value), SOC if without comments | D72: Units: %, if without explaination in the comments
B73: OC_T | C73: Organic carbon of treatment (mean value), SOC if without comments | D73: Units: %, if without explaination in the comments
B74: OC_Con_C | C74: Organic carbon of control (mean value) in units of concentration (Mg/ha)
B75: OC_Con_T | C75: Organic carbon of treatment (mean value) in units of concentration (Mg/ha)
B76: OC_Comments | C76: Soil organic carbon sequestration rate compare with beginning of experiments | D76: Seq. rate (Mg/ha/cm/yr), Always make comments
B77: OC_Change_C | C77: Soil organic carbon sequestration rate compare with beginning of experiments | D77: Seq. rate (Mg/ha/cm/yr), Always make comments
B78: OC_Change_T | C78: Comments on soil organic carbon sequestration rate compare with beginning of experiments | D78: Seq. rate (Mg/ha/cm/yr), Always make comments
B79: OC_Change_Comments
A80: 5 | B80: N_C | C80: Nitrogen of control (mean value), total nitrogen if without comments | D80: Units: mg kg-1 soil if without explaination in the comments
B81: N_T | C81: Nitrogen of treatment (mean value), total nitrogen if without comments | D81: Units: mg kg-1 soil if without explaination in the comments
B82: N_Comments | C82: Comments on nitrogen of treatment | D82: Always make comments
A83: 6 | B83: P_C | C83: Phosphorus of control (mean value) | D83: Units: mg kg-1 soil if without explaination in the comments
B84: P_T | C84: Phosphorus of treatment (mean value) | D84: Units: mg kg-1 soil if without explaination in the comments
B85: P_Comments | C85: Comments on phosphorus of treatment | D85: Always make comments
A86: 7 | B86: K_C | C86: Potassium of control (mean value) | D86: Units: mg kg-1 soil if without explaination in the comments
B87: K_T | C87: Potassium of treatment (mean value) | D87: Units: mg kg-1 soil if without explaination in the comments
B88: K_Coments | C88: Comments on potassium of treatment | D88: Always make comments
A89: 8 | B89: pH_C | C89: pH of control (mean value) | D89: No unit
B90: pH_T | C90: pH of treatment (mean value) | D90: No unit
B91: pH_Comments | C91: Comments on pH of treatment | D91: Make comments if necessary
A92: 9 | B92: CEC_C | C92: CEC of control (mean value) | D92: Units: cmolc kg-1 if without explaination in the comments
B93: CEC_T | C93: CEC of treatment (mean value) | D93: Units: cmolc kg-1 if without explaination in the comments
B94: CEC_Comments | C94: Comments on CEC of treatment | D94: Always make comments
A95: 10 | B95: EC_C | C95: Electric Conductivity of control (mean value) | D95: Units: dS m–1 if without explaination in the comments
B96: EC_T | C96: Electric Conductivity of treatment (mean value) | D96: Units: dS m–1 if without explaination in the comments
B97: EC_Comments | C97: Comments on EC of treatment | D97: Always make comments
A98: 11 | B98: BS_C | C98: Base Satuation of control (mean value) | D98: Units: mg kg-1 soil if without explaination in the comments
B99: BS_T | C99: Base Satuation of treatment (mean value) | D99: Units: mg kg-1 soil if without explaination in the comments
B100: BS_Comments | C100: Comments on Base Satuatio of treatment | D100: Always make comments
A101: 12 | B101: Aggre_C | C101: Soil aggregation of control (mean value), there are multiple indicators of soil aggregation, always make notes. Agg is a measure of how well soil aggregates resist disintegration when hit by rain drops. It is measured using a standardized simulated rainfall event on a sieve containing soil aggregates between 0.25 and 2.0 mm. The fraction of soil that remains on the sieve determines the percent aggregate stability. | D101: Units varied: g/kg if without explaination in the comments
B102: Aggre_T | C102: Soil aggregation of treatment (mean value), there are multiple indicators of soil aggregation, always make notes | D102: Units varied: g/kg if without explaination in the comments
B103: Aggre_Comments | C103: Comments on Soil aggregation of treatment, there are multiple indicators of soil aggregation, always make notes | D103: Always make comments
...

Sheet ExperimentID

Sheet UnitsConvertion
B3: Soil water content (SWC) units conversion
B4: Unit | C4: Conversion_factor | D4: Sample_土壤含水量 | E4: cm3/cm3 | F4: Notes
B5: g/cm3 | C5: BD | D5: 1 | E5: 1*BD | F5: VWC=GWC*BD
B6: g/g | C6: BD | D6: 1 | E6: 1*BD | F6: g/g=cm3/cm3 * BD
B7: mm | C7: =100/300 -> 0.33333333 | F7: No. 46 | G7: VMW
B9: more
B13: Soil bulk density units conversion
B14: Unit | C14: Conversion_factor | D14: Sample_土壤容重 | E14: g/cm3 | F14: Notes
B15: Mg/m3 | C15: 1 | D15: 1 | E15: 1 | F15: 1 Mg/m3 = 1 g/cm3 (1Mg = 1 million g = 10^6 g)
B18: need update
B21: Yield/weed/biomass/erosion
B22: Unit | C22: Conversion_factor | D22: Sample_土壤容重 | E22: kg/ha | F22: Notes
B23: g/m2 | C23: 10 | D23: 1 | E23: =C23*D23 -> 10 | F23: 1 g/m² x 1 kg/1000 g x 10000 m²/ha = 10 kg/ha = 10 kg/hm2
B24: Mg / ha | C24: 1000 | D24: 1 | E24: =C24*D24 -> 1000 | F24: 1 Mg = 1000000 g = 1000 kg/ha
B25: t/ha | C25: 1000 | D25: 1 | E25: =C25*D25 -> 1000
B26: pounds/acre | C26: =0.4536/0.4047 -> 1.1208302 | D26: 1 | F26: 1 acre = 0.4047 ha | H26: 1pound=0.4536kg
B28: more
B32: SOC
B33: Unit | C33: Conversion_factor | D33: Sample_土壤容重 | E33: %
B34: g/kg | C34: 0.1 | D34: 1 | E34: =D34*C34 -> 0.1 | F34: 1 g/kg = 0.1 % | M34: MG | N34: kg
B35: t/ha | C35: =1000/1627500*100 -> 0.061443932 | D35: 1 | E35: =D35*C35 -> 0.061443932 | F35: 1 ha = 100*100*0.075*1.4Mg | I35: 1627500 Kg when BD = 1.085 (Study No. 13) | M35: =(100*100*0.1*1.37) -> 1370 | N35: =M35*1000 -> 1370000
B36: kg/ha | C36: =1/N35*100 -> 7.2992701e-05 | D36: 1 | E36: =D36*C36 -> 7.2992701e-05 | F36: No40
B37: Mg/ha | C37: =1/M35*100 -> 0.072992701 | D37: 1 | E37: =D37*C37 -> 0.072992701 | F37: No40 | M37: =1/(100*100*0.05*1.35)*100 -> 0.14814815 | N37: =1/(100*100*0.1*1.57)*100 -> 0.063694268 | O37: =1/(100*100*0.15*1.59)*100 -> 0.041928721
B38: Kg/Mg | C38: 0.1 | D38: 1 | E38: =D38*C38 -> 0.1 | M38: =1/(100*100*0.05*1.39)*100 -> 0.14388489 | N38: =1/(100*100*0.1*1.62)*100 -> 0.061728395 | O38: =1/(100*100*0.15*1.57)*100 -> 0.042462845
B39: g/m2 | F39: depth = 0.3 | G39: BD=1.2 | H39: 1m2 = 1*1*0.3*1.2 Mg
B40: OM | C40: =1/1.72 -> 0.58139535
B41: more
B43: Soil N (TN, Inorganic N, NO3-N, NH4-N, Nox, NHx, Nox+NHx) | J43: No.17,D=1.2, BS=1.25 | K43: No.73
B44: Unit | C44: Conversion_factor | D44: Sample_土壤容重 | E44: mg kg-1 soil | I44: 1 ha = Mg | J44: 1 ha = Kg | K44: 1 ha = Kg
B45: kg/ha | C45: =1000000/K45 -> 0.056003584 | D45: 1 | E45: =D45*C45 -> 0.056003584 | I45: =100*100*0.6*1.5 -> 9000 | J45: =I45*1000 -> 9000000 | K45: =100*100*1.2*1.488*1000 -> 17856000
B46: % | C46: 10000 | D46: 1 | E46: =D46*C46 -> 10000 | F46: %=0.01g/g | G46: 10mg/g | H46: 10000 mg / kg
B47: g/kg | C47: 1000 | D47: 1 | E47: =D47*C47 -> 1000
B48: PPM | C48: 1 | D48: 1 | E48: =D48*C48 -> 1 | F48: ppm=0.0001%
B49: mg/g | C49: 1 | D49: 1 | E49: =D49*C49 -> 1
B50: g/m2 | C50: =1000/G50 -> 1.52207 | D50: 1 | E50: =D50*C50 -> 1.52207 | F50: 1m2=657kg | G50: =1.46*100*100*45/1000 -> 657 | I50: No.70
B51: more
B53: SIR or CO2 Burst Test
B54: Unit | C54: Conversion_factor | D54: Sample_土壤容重 | E54: mg CO2 kg−1 soil d−1
B55: mu mol CO2 /kg soil/ d | C55: =1/22.7273 -> 0.043999947 | D55: 1 | E55: =D55*C55 -> 0.043999947 | F55: 1 mg = 22.7273 mu mol | G55: 1 mu mol=1/1000000 mol | I55: =1/1000000*44*1000 -> 0.044
B56: n mol / g | C56: 0.044 | D56: 1 | E56: =D56*C56 -> 0.044 | F56: 1 nmol=1/1000000000 mol * 44 g/mol | I56: =1/1000000000*44*1000*1000 -> 0.044
B57: kg/ha/day | C57: =1000000/L57 -> 0.61443932 | D57: 1 | E57: =D57*C57 -> 0.61443932 | F57: 1 kg=10^6 mg | H57: 1 ha = 100*100*0.15*BD*1000 kg | L57: =100*100*0.15*1.085*1000 -> 1627500 | N57: Sno.13
B58: mu g C per g per day | C58: =1/1000000*1000*1000 -> 1 | D58: 1 | E58: =D58*C58 -> 1
B60: more
B62: MBC/K/MBN
B63: Unit | C63: Conversion_factor | D63: Sample_土壤容重 | E63: mg kg-1 soil
B64: n mol / g | C64: =1/1000000000*12*1000*1000 -> 0.012 | D64: 1 | E64: =C64*D64 -> 0.012 | F64: 1 nmol = 1/1000000000 mol | I64: 1mol=12g | J64: No29
B65: c mol / kg | C65: =0.01*12*1000 -> 120 | D65: 1 | E65: =C65*D65 -> 120 | F65: 1 cmol = 0.01 mol | J65: K need *39
B66: kg/ha | C66: =1000000/1627500 -> 0.61443932 | D66: 1 | E66: =D66*C66 -> 0.61443932 | F66: Sno.13 | G66: 1 ha = 1627.5Mg | H66: =100*100*0.15*1.085 -> 1627.5
B67: % | C67: =1000000/100 -> 10000 | D67: 1 | E67: =D67*C67 -> 10000
B68: more
B71: Microbe activity/Enzyme/nematode/earthwarm
B72: Unit | C72: Conversion_factor | D72: Sample_土壤容重 | E72: mu g g-1 soil
B73: n mol / g | C73: =1/1000000000*12*1000*1000 -> 0.012 | D73: 1 | E73: =C73*D73 -> 0.012 | G73: =1/1000000000*12*1000000 -> 0.012
B74: n mol / kg | C74: =C73/1000 -> 1.2e-05
B77: more
B80: Ks, Hydrulic conductivity
B81: Unit | C81: Conversion_factor | D81: Sample_土壤容重 | E81: cm/h
B82: mm / s | C82: =3600/10 -> 360 | D82: 1 | E82: =C82*D82 -> 360
B83: mm / min | C83: =60/10 -> 6 | D83: 1 | E83: =C83*D83 -> 6
B84: m / day | C84: =10/24 -> 0.41666667 | D84: 1 | E84: =D84*C84 -> 0.41666667
B87: more
B90: Soil erosion
B91: Unit | C91: Conversion_factor | D91: Sample_土壤容重 | E91: t/ha
B92: kg/ha | C92: 1000 | D92: =1/1000 -> 0.001 | E92: =C92*D92 -> 1
B93: lb/acre | C93: 1000 | D93: =0.4536/0.4/1000 -> 0.001134 | E93: =C93*D93 -> 1.134
B94: Mg / ha | C94: 1 | D94: 1 | E94: =D94*C94 -> 1
B95: g/m2 | C95: =10000/1000000 -> 0.01 | D95: 1 | E95: =D95*C95 -> 0.01
B97: more
B100: Runoff
B101: Unit | C101: Conversion_factor | D101: Sample_土壤容重 | E101: mm/yr
B102: % precipitation | E102: precip*prec entage
B103: L/m2 | C103: 1 | D103: 1 | E103: =C103*D103 -> 1
B104: 10^4L/ha | C104: 1 | D104: 1 | E104: =C104*D104 -> 1
B105: m3/ha | C105: 0.1 | D105: 1 | E105: =C105*D105 -> 0.1
B106: Drainage | E106: Precip-Drainage
B107: mm/day | D107: 1
B109: more

Sheet RsUnitsConvertion
A2: ID | B2: Unit | C2: Conversion | D2: Sample_flux | E2: Flux_in_umol CO2/m2/s
A3: 1 | B3: g C/m2/day | C3: 0.96450617 | D3: 1 | E3: =D3*C3 -> 0.96450617
A4: 2 | B4: g C/m2/hr | C4: 23.148148 | D4: 1 | E4: =D4*C4 -> 23.148148
A5: 3 | B5: g C/m2/yr | C5: 0.002642483 | D5: 1 | E5: =D5*C5 -> 0.002642483
A6: 4 | B6: g CO2/m2/day | C6: 0.26304714 | D6: 1 | E6: =D6*C6 -> 0.26304714
A7: 5 | B7: g CO2/m2/hr | C7: 6.3131313 | D7: 1 | E7: =D7*C7 -> 6.3131313
A8: 6 | B8: kg C/ha/day | C8: 0.096450617 | D8: 1 | E8: =D8*C8 -> 0.096450617
A9: 7 | B9: mg C/m2/day | C9: 0.000964506 | D9: 1 | E9: =D9*C9 -> 0.000964506
A10: 8 | B10: mg C/m2/hr | C10: 0.023148148 | D10: 1 | E10: =D10*C10 -> 0.023148148
A11: 9 | B11: mg CO2/m2/day | C11: 0.000263047 | D11: 1 | E11: =D11*C11 -> 0.000263047
A12: 10 | B12: mg CO2/m2/hr | C12: 0.006313131 | D12: 1 | E12: =D12*C12 -> 0.006313131
A13: 11 | B13: mg CO2/m2/s | C13: 22.727273 | D13: 1 | E13: =D13*C13 -> 22.727273
A14: 12 | B14: mmol CO2/m2/day | C14: 0.011574074 | D14: 1 | E14: =D14*C14 -> 0.011574074
... A22: 20 | B22: umol CO2/m2/s | C22: 1 | D22: 1 | E22: =D22*C22 -> 1

Sheet SoilClassfication
B2: USDA soil classification
B3: SOIL ORDER | C3: SOIL | D3: DESCRIPTION | E3: SOIL FAMILY
B4: ALFISOLS
C5: Soil 1 | D5: Fine_loamy, mixed | E5: Typic Cryoboralfs
C6: Soil 2 (Santa Series) | D6: Coarse-silty, mixed, frigid | E6: Ochreptic Fragixeralfs
C7: Soil 3 (Porthill Series) | D7: Fine, mixed, frigid Typic | E7: Hapioxeralfs
B8: ARIDISOLS
C9: Soil 4 (Chilcott Series) | D9: Fine, montmorillonitic, mesic | E9: Abruptic Xerollic Durargids
C10: Soil 5 (Colthorp Series) | D10: Loamy, mixed, mesic, shallow | E10: Xerollic Durargids
C11: Soil 6 (Sebree Series) | D11: Fine-silty, mixed, mesic | E11: Xerollic Nadurargids
C12: Soil 7 (Gooding Series) | D12: Fine, montmorillonitic, mesic | E12: Xerollic Paleargids
C13: Soil 8 (Portneuf Series) | D13: Coarse-silty, mixed, mesic | E13: Durixerollic Calciorthids
C14: Soil 9 (Trevino Series | D14: Loamy, mixed, mesic Lithic | E14: Xerollic Camborthids
C15: Soil IO (Owhyee Series) | D15: Coarse-silty, mixed, mesic | E15: Xerollic Camborthids
C16: Soil 11 (Minidoka Series) | D16: Coarse-silty, mixed, mesic | E16: Xerollic Durorthids
C17: Soil 12 | D17: Loamy, mixed, frigid | E17: Xerollic Durorthids
B18: ENTISOLS
C19: Soil 13 (Garbutt Series) | D19: Coarse-silty, mixed (calcareous), mesic | E19: Typic Torriorthents
C20: Soil 14 (Flybow Series) | D20: Loamy-skeletal, mixed, monacid, mesic | E20: Lithic Xerorthents
C21: Soil 15 (Pyle Series) | D21: Mixed | E21: Alfic Cryopsamments
C22: Soil 16 (Gruincy Series) | D22: Mixed, mesic | E22: Xeric Torripsamments
C24: Soil 17 (Shollrock Series) | D24: Mixed, frigid | E24: Typic Xeropsamments
B25: HISTISOLS
C26: Soil 18 (Pywell Series) | E26: Euic Typic Borosaprists
B27: INCEPTISOLS
C28: Soil 19 (Vay Series) | D28: Medial over loamy-skeletal, mixed | E28: Entic Cryandepts
C29: Soil 20 (Bluehill Series) | D29: Ashy, mesic | E29: Typic Vitrandepts
C30: Soil 21 | D30: Medial over loamy, mixed, frigid | E30: Typic Vitrandepts
C31: Soil 22 (Moonville Series) | D31: Cindery, frigid | E31: Mollic Vitrandepts
C32: Soil 23 (Roseberry Series) | D32: Sandy, mixed | E32: Humic Cryaquepts
C33: Soil 24 | D33: Loamy-skeletal, mixed | E33: Andic Cryochrepts
C34: Soil 25 | D34: Loamy-skeletal, mixed | E34: Dystric Cryochrepts
C35: Soil 26 | D35: Fine-loamy, mixed | E35: Dystric Cryochrepts
C36: Soil 27 | D36: Coarse-loamy, mixed, frigid | E36: Andic Dystrochrepts
C37: Soil 28 (Moonville Variant) | D37: Coarse-loamy, mixed, frigid | E37: Andic Xerochrepts
C38: Soil 29 (Bonner Series) | D38: Coarse-loamy over sandy or sandy skeletal, mixed, frigid | E38: Andic Xerochrepts
C39: Soil 30 (Oxford Series) | D39: Fine, montmorillonitic, frigid | E39: Vertic Xerochrepts
... C41: Soil 32 | D41: Coarse-loamy, mixed | E41: Andic Cryumbrepts
B42: MOLLISOLS
C43: Soil 33 (Southwick Series) | D43: Fine-silty, mixed, mesic | E43: Argiaquic Xeric Argialbolls
C44: Soil 34 (Houk Series) | D44: Fine, montmorillonitic, frigid | E44: Argiaquic Xeric Argialbolls
C45: Soil 35 (Nez Perce Series) | D45: Fine, montmorillonitic, mesic | E45: Xeric Argialbolls
C46: Soil 36 (Drigge Variant) | D46: Fine-loamy, mixed | E46: Argic Cryoborrolls
C47: Soil 37 | D47: Fine-loamy, mixed | E47: Argic Pachic Cryoborolls
C48: Soil 38 (Greys Series) | D48: Fine-silty, mixed | E48: Boralfic Cryoboroils
C49: Soil 39 | D49: Very fine, mixed | E49: Duric Cryoborolls
C50: Soil 40 (Pavohroo Series) | D50: Fine-loamy, mixed | E50: Pacfic Cryoborolls
C51: Soil 41 (Tannehill Series) | D51: Loamy-skeletal, mixed mesic | E51: Calcic Argixerolis
C52: Soil 42 (Gem Series) | D52: Fine, montmorillonitic, mesic | E52: Calcic Argixerolls
C53: Soil 43 (Gwin Series) | D53: Loamy-skeletal, mixed, mesic | E53: Lithic Argixerolls
C54: Soil 44 (Kilckson Series) | D54: Loamy-skeletal, mixed, frigid | E54: Ultic Argixerolis
... C60: Soil 50 (Palouse Series) | D60: Fine-silty, mixed, mesic | E60: Pachic Ultic Haploxerolls
B61: SPODOSOLS
C62: Soil 51 | D62: Coarse-loamy, mixed | E62: Entic Cryorthods
B63: VERTISOLS
C64: Soil 52 (Magic Series) | D64: Fine, montmorillonitic, frigid | E64: Entic Chromoxererts
C65: Soil 53 (Agar Series) | D65: Very fine, montmorillonitic, mesic | E65: Entic Chromoxererts
C66: Soil 54 (Boulder Lake Series) | D66: Very fine, montmorillonitic, frigid | E66: Chromic Pelloxererts
B69: FAO soil classification | C69: http://www.fao.org/docrep/003/y1899e/y1899e02.htm
B70: SET #1 | C70: Organic soils | D70: HISTOSOLS
B71: SET #2 | C71: Mineral soils whose formation was conditioned by human influences (not confined to any particular region) | D71: ANTHROSOLS
B72: SET #3 | C72: Mineral soils whose formation was conditioned by their parent material | D72: Andosols
C73: - Soils developed in volcanic material | D73: ARENOSOLS
C74: - Soils developed in residual and shifting sands | D74: VERTISOLS
C75: - Soils developed in expanding clays
B76: SET #4 | C76: Mineral soils whose formation was conditioned by the topography/physiography of the terrain | D76: FLUVISOLS
C77: - Soils in lowlands (wetlands) with level topography | D77: GLEYSOLS
C78: - Soils in elevated regions with non-level topography | D78: LEPTOSOLS
D79: REGOSOLS
B80: SET #5 | C80: Mineral soils whose formation is conditioned by their limited age (not confined to any particular region) | D80: CAMBISOLS
B81: SET #6 | C81: Mineral soils whose formation was conditioned by climate: (sub-)humid tropics | D81: PLINTHOSOLS
D82: FERRALSOLS
D83: NITISOLS
D84: ACRISOLS
D85: ALISOLS
D86: LIXISOLS
B87: SET #7 | C87: Mineral soils whose formation was conditioned by climate: arid and semi-arid regions | D87: SOLONCHAKS
D88: SOLONETZ
D89: GYPSISOLS
D90: DURISOLS
D91: CALCISOLS
B92: SET #8 | C92: Mineral soils whose formation was conditioned by climate: steppes and steppic regions | D92: KASTANOZEMS
D93: CHERNOZEMS
D94: PHAEOZEMS
B95: SET #9 | C95: Mineral soils whose formation was conditioned by climate: (sub-)humid temperate regions | D95: PODZOLS
D96: PLANOSOLS
D97: ALBELUVISOLS
D98: LUVISOLS
D99: UMBRISOLS
B100: SET #10 | C100: Mineral soils whose formation was conditioned by climate: permafrost regions

Sheet SoilDepth

Sheet CoverCropGroup
B1: CoverCrop | C1: MiddleGroup | D1: TopGroup | E1: Comments
B2: Brassica | C2: Brassica | D2: Broadleaf | E2: Single cover crop
B3: Broccoli | E3: Single cover crop
B4: Colza | E4: Single cover crop
B5: Canola | E5: Single cover crop
B6: Radish | E6: Single cover crop
B7: Rapeseed | E7: Single cover crop
B8: Sorghum-sudangrass | E8: Single cover crop
B9: Turnip | E9: Single cover crop
B10: White_mustard | E10: Single cover crop
B11: Sunflower | C11: Broadleaf | E11: Single cover crop
B12: Phacelia | E12: Single cover crop
B13: Barley | C13: Grass | D13: Grass | E13: Single cover crop
B14: Buckwheat | E14: Single cover crop
B15: Canada_bluegrass | E15: Single cover crop
B16: Common_chickweed | E16: Single cover crop
B17: Gamagrass | E17: Single cover crop
B18: Hemp | E18: Single cover crop
B19: Millet | E19: Single cover crop
B20: Oat/ Saia oat | E20: Single cover crop
B21: Tartary_Buckwheat | E21: Single cover crop
B22: Triticale | E22: Single cover crop
B23: Trudan | E23: Single cover crop
B24: Wheat | E24: Single cover crop
B25: Barley | C25: Rye | E25: Single cover crop
B26: Cereal | E26: Single cover crop
B27: Downy_brome | E27: Single cover crop
B28: Italian_Rye_grass | E28: Single cover crop
B29: Rye | E29: Single cover crop
B30: Rye_grass | E30: Single cover crop
B31: Alfalfa | C31: Legume | D31: Legume | E31: Single cover crop
B32: Austrian_winter_pea | E32: Single cover crop
B33: Clover | E33: Single cover crop
B34: Common_Vetch | E34: Single cover crop
B35: Crimson_clover | E35: Single cover crop
B36: Crown_Vetch | E36: Single cover crop
B37: Forage_pea | E37: Single cover crop
B38: Hairy_vetch | E38: Single cover crop
B39: Kura_clover | E39: Single cover crop
B40: Legume | E40: Single cover crop
B41: Lentil | E41: Single cover crop
B42: Lupine | E42: Single cover crop
B43: Pea | E43: Single cover crop
... B51: White_clover | E51: Single cover crop
B52: Gliricidia | C52: Legume_Tree | E52: Single cover crop
B53: Leucaena | C53: Legume_Tree | E53: Single cover crop
B55: Mixed | C55: BG | E55: Mixed of brassica and grass
B56: Mixed | C56: LB | D56: Mixed | E56: Mixed of legume and brassica
B57: Mixed | C57: LG | E57: Mixed of legume and grass
B58: Mixed | C58: LL | E58: Mixed of legume and legume
B59: Mixed of two | C59: MOT | E59: Mixed of other two cover crops
B60: Mixed | C60: MMT | E60: Mixed of more than three
B61: Average of combination of above | C61: AVG | D61: AVG | E61: Average results from several cover crops

Sheet GrainCropGroup
B1: GrainrCrop | C1: MiddleGroup | D1: TopGroup | E1: Comments
B2: Corn | C2: Corn | D2: Monoculture | E2: Monoculture
B3: Sweetcorn | E3: Monoculture
B4: Maize | E4: Monoculture
B5: Soybean | C5: Soybean | E5: Monoculture
E6: Monoculture
B7: Wheat | C7: Wheat | E7: Monoculture
E8: Monoculture
B9: Average of the conbination of above | C9: AVG | E9: Monoculture
B10: Sorghum | C10: Arable | E10: Monoculture
B11: Cotton | E11: Monoculture
B12: Cassava | E12: Monoculture
B13: Oat | E13: Monoculture
B14: Rice | E14: Monoculture
B15: Barley | E15: Monoculture
B16: Tobaco | E16: Monoculture
C17: Corn-soybean | D17: Rotation of two | E17: ROT
C18: Corn-wheat | E18: ROT
C19: Wheat_soybean | E19: ROT
C20: Rotation of other two | E20: ROT
C21: Corn-soybean-wheat | D21: Rotation of three or more | E21: ROT
C22: Rotation of other three | E22: MTT
C23: Rotation of more than three | E23: MTT
B24: Apricot | C24: Orchard | E24: Orchard
B25: Tea | E25: Orchard
B26: Coffee | E26: Orchard
B27: Guava | E27: Orchard
B28: Apple | E28: Orchard
B29: GRAPEVINE | E29: Orchard
B30: Kiwifruit | E30: Orchard
B31: Radix glycyrrhizar and Isatis tinctoria | E31: Orchard
B32: Indigowoad, Liquorice | E32: Orchard
B33: Grassland | C33: Pasture | E33: Pasture
B34: Cucumber | C34: Vegetable | E34: Vegetable
B35: Cowpea | E35: Vegetable
B36: Drybean | E36: Vegetable
B37: Pea | E37: Vegetable
B38: Chickpea | E38: Vegetable
B39: Beens | E39: Vegetable
B40: Tomato | E40: Vegetable
B41: Squash | E41: Vegetable
B42: Shepherd's-purse | E42: Vegetable
B43: Beet | E43: Vegetable
B44: Pepper | E44: Vegetable
B45: okra | E45: Vegetable
B46: Zucchini | E46: Vegetable
... B48: Watermelon | E48: Vegetable
B49: Not reported, or the results are from the average of multiple cash crops | C49: AVG | D49: AVG | E49: Not reported, or the results are from the average of multiple cash crops

Sheet TillageGroup
C1: Tillage details | D1: MiddleGroup | E1: TopGroup | F1: Comments
C2: Disk tillage | D2: Conventional tillage | E2: CT
C3: Sweep | D3: Conventional tillage | E3: CT
C4: Tandem disk | D4: Conventional tillage | E4: CT
C5: Full-tilled | D5: Conventional tillage | E5: CT
C6: Mouldboard ploughing | D6: Conventional tillage | E6: CT
C7: Harrowing | D7: Conventional tillage | E7: CT
C8: Moldboard plowing | D8: Conventional tillage | E8: CT
C9: Turnplow | D9: Conventional tillage | E9: CT
C10: Plow-till | D10: Conventional tillage | E10: CT
C11: Ridge-till | D11: Conventional tillage | E11: CT
C12: Multch tillage | D12: Reduced tillage | E12: RT
C13: Chisel | D13: Reduced tillage | E13: RT
... C18: No-tillage | D18: No-tillage | E18: NT

Sheet SD_SE
B1: Equation | C1: Comments
B2: se = sd / sqrt(N) | C2: N = replication if without explaination
B3: sd = se * sqrt(N) | C3: N = replication if without explaination
B4: sd=cv*mean | C4: cv - coefficient of variation
B5: sd = 95%CI/1.96 * sqrt(N) | C5: CI - confidence interval

Sheet Notes
A1: ID | B1: Description | C1: StudyID | D1: Sign | E1: Notes 1 | F1: Notes 2
A2: 1 | B2: Not use | C2: 60 | D2: Average | E2: Yield is measured but not reported, use average represent
A3: 2 | B3: NO3-N, NH4-N == Nmin?
A4: 3 | B4: Always add comments, units, whether have units convert, etc.
A5: 4 | B5: Do not mix up control and treatment
A6: 5 | B6: Backgroud information and response data should always match
A7: 6 | B7: Soil depth, top layer, surface layer, need see soil sampling description
A8: 7 | B8: Units for OC is % or Mg per ha
A9: 8 | B9: ExperimentID added
A10: 9 | B10: Double check Soil_OC base line
A11: 10 | B11: Heavy material | E11: Heavy metals such as arsenic, barium, cadmium, chromium, copper, lead, nickel, zinc are measured. | F11: Can be added

Sheet References
A1: StudyID | B1: References
A2: 1 | B2: Abawi, G. S. & Widmer, T. L. Impact of soil health management practices on soilborne pathogens, nematodes and root diseases of vegetable crops. Appl. Soil Ecol. 15, 37–47 (2000).
A3: 2 | B3: Bandick, A. K. & Dick, R. P. Field management e  ects on soil enzyme activities. Soil Biol. Biochem. 31, 1471–1479 (1999).
A4: 3 | B4: Blackshaw, R. E. Agronomic merits of cereal cover crops in dry bean production systems in western Canada. Crop Prot. 27, 208–214 (2008).
A5: 4 | B5: Blanco-Canqui, H., Mikha, M. M., Presley, D. R. & Claassen, M. M. Addition of Cover Crops Enhances No-Till Potential for Improving Soil Physical Properties. Soil Sci. Soc. Am. J. 75, 1471 (2011).
A6: 5 | B6: Blanco-Canqui, H., Holman, J. D., Schlegel, A. J., Tatarko, J. & Shaver, T. M. Replacing Fallow with Cover Crops in a Semiarid Soil: Effects on Soil Properties. Soil Sci. Soc. Am. J. 77, 1026 (2013).
A7: 6 | B7: Bloszies, S. A. Soil Microbial Activity and Organic Carbon Dynamics in Low Input Agroecosystems. (North Carolina State University, 2016).
A8: 7 | B8: Bottomley, P. J., Sawyer, T. E., Boersma, L., Dick, R. P. & Hemphill, D. D. Winter cover crop enhances 2,4-D mineralization potential of surface and subsurface soil. Soil Biol. Biochem. 31, 849–857 (1999).
A9: 8 | B9: Brainard, D. C., Bryant, A., Noyes, D. C., Haramoto, E. R. & Szendrei, Z. Evaluating pest-regulating services under conservation agriculture: A case study in snap beans. Agric.
A10: 9 | B10: Bruce, R. R., Langdale, G. W., West, L. T. & Miller, W. P. Soil surface modification by biomass inputs affecting rainfall infiltration. Soil Sci. Soc. Am. J. 56, 1614–1620 (1992).
A11: 10 | B11: Bulan, M. T. S., Stoltenberg, D. E. & Posner, J. L. Buckwheat species as summer cover crops for weed suppression in no-tillage vegetable cropping systems. Weed Sci. 63, 690–702 (2015).
A12: 11 | B12: Buyer, J. S., Teasdale, J. R., Roberts, D. P., Zasada, I. A. & Maul, J. E. Factors affecting soil microbial community structure in tomato cropping systems. Soil Biol. Biochem. 42, 831–841 (2010).
A13: 12 | B13: Campbell, R. B., Sojka, R. E. & Karlen, D. L. Conservation tillage for soybean in the US southeastern cosstal plain. Soil Tillage Res. 4, 531–541 (1984).
... A282: 281 | B282: Domagała-Świątkiewicz, I. & Gąstoł, M. Soil chemical properties under organic and conventional crop management systems in south Poland. Biol. Agric. Hortic. 29, 12–28 (2013).
A283: 282 | B283: Qi, Y., Cui, Q., Zhou, B. & Gao, Z. Effects of Different Winter-Planting Green Manures on Yield and Quality of Flue-cured Tobacco in South Anhui Tobacco Areas. Chinese Tob. Sci. 37, 32–36 (2016).
A284: 283 | B284: WANG, B. et al. Improvement Effect of Different Green Manure Crops on Dwarf Apple Orchard Soil in Southern Yan’an. J. Shanxi Agric. Sci. 44, 1643–1645 (2016).
A285: 284 | B285: YANG, C., ZHAO, Z., YANG, L. & LI, X. Effect of green manure mulching on soil physical and chemical property in Yunnan Rubber Plantation. in Proceedings of the fourth national agricultural environmental science symposium 367–375 (2011).
A286: 285 | B286: Sun, J., Liu, M., Li, L., Liu, J. & Sayre., K. D. Effects of tillage mode on soil erosion on rain-fed cropland in Inner Mongolia. Chinese J. Ecol. 29, 485–490 (2010).
A287: 286 | B287: Fu, Q., Luo, Y. & Chai, X. Ecological Effects and Economic Bencfit of the Complex Agro-Forestry Systems in Low-Hilland Red Soil Areas. Chinese J. Ecol. 14, 11–15 (1995).
A288: 287 | B288: Xu, P. Experimental study on soil erosion prevention and cure with conservation tillage in Jilin region. (Northeast Normal University, 2006).
A289: 288 | B289: USDA-ARS. USDA agriculture handbooks. (1979).
A290: 289 | B290: Leys, J. F. & Heinjus, D. Simulated wind erosion in the South Australian Murray Mallee. (Conservation Service of NSW, 1991).
A291: 290 | B291: Zhao, J. F., Huang, G. B., Xin, P., Xie, K. Z. & Xu, A. X. Runoff and quantity of soil erosion under conservation tillage system by simulated rainfall. Bull. Soil Water Conserv. 27, 16–19 (2007).
A292: 291 | B292: Tan, C. Effects of conservation tillage on the soil nutrients maintenance and control of water erosion of sloping farmland. (Northwest A&F University, 2015).
A293: 292 | B293: ZHAO, X., WANG, H., LI, L. & CUI, T. Impact of conservation tillage on crop growth and soil and water retaining under grain-legume-grass strip intercropping in slope land. Agric. Res. Arid Areas 31, 7–30 (2013).
A294: 293 | B294: Zhang, Y., Xu, X., Sui, Y. & Lu, G. The research of the influence of conservation tillage on the soil conservation in sloping black soil zone. Jilin Water Resour. 11, 1–5 (2012).
... A322: 321 | B322: Banda, A. Z., J. A. Maghembe, D. N. Ngugi, and V. A. Chome. Effect of intercropping maize and closely spacedLeucaena hedgerows on soil conservation and maize yield on a steep slope at Ntcheu, Malawi. Agroforestry systems 27, no. 1, 17-22 (1994).

Sheet Sheet2
A1: StudyID | B1: References1 | C1: StudyID | D1: References2
A2: 1 | B2: Aase, J. K., Schaefer, G. M. & Pikul, J. L. Hayland conversion to wheat production in semiarid eastern Montana: Tillage, yield and hay production comparisons. Soil Tillage Res. 44, 225–234 (1997). | C2: 1 | D2: Abawi, G. S. & Widmer, T. L. Impact of soil health management practices on soilborne pathogens, nematodes and root diseases of vegetable crops. Appl. Soil Ecol. 15, 37–47 (2000).
A3: 2 | B3: Abidela Hussein, M. et al. Deep tillage improves degraded soils in the (sub) humid Ethiopian highlands. Land 8, 159 (2019). | C3: 2 | D3: Bandick, A. K. & Dick, R. P. Field management e  ects on soil enzyme activities. Soil Biol. Biochem. 31, 1471–1479 (1999).
A4: 3 | B4: Acharya, B. S. et al. Winter cover crops effect on soil moisture and soybean growth and yield under different tillage systems. Soil Tillage Res. 195, 104430 (2019). | C4: 3 | D4: Blackshaw, R. E. Agronomic merits of cereal cover crops in dry bean production systems in western Canada. Crop Prot. 27, 208–214 (2008).
A5: 4 | B5: Adimassu, Z., Alemu, G. & Tamene, L. Effects of tillage and crop residue management on runoff, soil loss and crop yield in the Humid Highlands of Ethiopia. Agric. Syst. 168, 11–18 (2019). | C5: 4 | D5: Blanco-Canqui, H., Mikha, M. M., Presley, D. R. & Claassen, M. M. Addition of Cover Crops Enhances No-Till Potential for Improving Soil Physical Properties. Soil Sci. Soc. Am. J. 75, 1471 (2011).
A6: 5 | B6: Ahmed, W. et al. Tillage practices improve rice yield and soil phosphorus fractions in two typical paddy soils. J. Soils Sediments 20, 850–861 (2020). | C6: 5 | D6: Blanco-Canqui, H., Holman, J. D., Schlegel, A. J., Tatarko, J. & Shaver, T. M. Replacing Fallow with Cover Crops in a Semiarid Soil: Effects on Soil Properties. Soil Sci. Soc. Am. J. 77, 1026 (2013).
A7: 6 | B7: Ahrens, W. H. & Endres, G. J. Trifluralin and ethalfluralin granules in conservation-tillage soybeans (Glycine max). Can. J. Plant Sci. 76, 891–897 (1996). | C7: 6 | D7: Bloszies, S. A. Soil Microbial Activity and Organic Carbon Dynamics in Low Input Agroecosystems. (North Carolina State University, 2016).
A8: 7 | B8: Alam, M. et al. Banding of fertilizer improves phosphorus acquisition and yield of zero tillage maize by concentrating phosphorus in surface soil. Sustainability 10, 3234 (2018). | C8: 7 | D8: Bottomley, P. J., Sawyer, T. E., Boersma, L., Dick, R. P. & Hemphill, D. D. Winter cover crop enhances 2,4-D mineralization potential of surface and subsurface soil. Soil Biol. Biochem. 31, 849–857 (1999).
A9: 8 | B9: Ali, S., Tedone, L., Verdini, L., Cazzato, E. & De Mastro, G. Wheat response to no-tillage and nitrogen fertilization in a long-term faba bean-based rotation. Agronomy 9, 50 (2019). | C9: 8 | D9: Brainard, D. C., Bryant, A., Noyes, D. C., Haramoto, E. R. & Szendrei, Z. Evaluating pest-regulating services under conservation agriculture: A case study in snap beans. Agric.
A10: 9 | B10: Almaraz, J. J. et al. Greenhouse gas fluxes associated with soybean production under two tillage systems in southwestern Quebec. Soil Tillage Res. 104, 134–139 (2009). | C10: 9 | D10: Bruce, R. R., Langdale, G. W., West, L. T. & Miller, W. P. Soil surface modification by biomass inputs affecting rainfall infiltration. Soil Sci. Soc. Am. J. 56, 1614–1620 (1992).
A11: 10 | B11: Almaraz, J. J. et al. Carbon Dioxide and Nitrous Oxide Fluxes in Corn Grown under Two Tillage Systems in Southwestern Quebec. Soil Sci. Soc. Am. J. 73, 113–119 (2009). | C11: 10 | D11: Bulan, M. T. S., Stoltenberg, D. E. & Posner, J. L. Buckwheat species as summer cover crops for weed suppression in no-tillage vegetable cropping systems. Weed Sci. 63, 690–702 (2015).
A12: 11 | B12: Anapalli, S. S. et al. Effectiveness of RZWQM for simulating alternative great plains cropping systems. Agron. J. 97, 1183–1193 (2005). | C12: 11 | D12: Buyer, J. S., Teasdale, J. R., Roberts, D. P., Zasada, I. A. & Maul, J. E. Factors affecting soil microbial community structure in tomato cropping systems. Soil Biol. Biochem. 42, 831–841 (2010).
A13: 12 | B13: Andales, A. A., Batchelor, W. D., Anderson, C. E., Farnham, D. E. & Whigham, D. K. Incorporating tillage effects into a soybean model. Agric. Syst. 66, 69–98 (2000). | C13: 12 | D13: Campbell, R. B., Sojka, R. E. & Karlen, D. L. Conservation tillage for soybean in the US southeastern cosstal plain. Soil Tillage Res. 4, 531–541 (1984).
... A282: 281 | B282: Plaza-Bonilla, D. et al. No-tillage reduces long-term yield-scaled soil nitrous oxide emissions in rainfed Mediterranean agroecosystems: A field and modelling approach. Agric. Ecosyst. Environ. 262, 36–47 (2018). | C282: 281 | D282: Domagała-Świątkiewicz, I. & Gąstoł, M. Soil chemical properties under organic and conventional crop management systems in south Poland. Biol. Agric. Hortic. 29, 12–28 (2013).
A283: 282 | B283: Potter, K. N., Morrison, J. E. & Torbert, H. A. Tillage intensity effects on corn and grain sorghum growth and productivity on a vertisol. J. Prod. Agric. 9, 385–390 (1996). | C283: 282 | D283: Qi, Y., Cui, Q., Zhou, B. & Gao, Z. Effects of Different Winter-Planting Green Manures on Yield and Quality of Flue-cured Tobacco in South Anhui Tobacco Areas. Chinese Tob. Sci. 37, 32–36 (2016).
A284: 283 | B284: Pradhan, P. R. et al. Tillage and crop residue management practices on crop productivity, phosphorus uptake and forms in wheat (Triticum aestivum)-based cropping systems. Indian J. Agric. Sci. 81, 1168–1173 (2011). | C284: 283 | D284: WANG, B. et al. Improvement Effect of Different Green Manure Crops on Dwarf Apple Orchard Soil in Southern Yan’an. J. Shanxi Agric. Sci. 44, 1643–1645 (2016).
A285: 284 | B285: Qin, J. et al. The effect of mulching, tillage and rotation on yield in non-flooded compared with flooded rice production. J. Agron. Crop Sci. 196, 397–406 (2010). | C285: 284 | D285: YANG, C., ZHAO, Z., YANG, L. & LI, X. Effect of green manure mulching on soil physical and chemical property in Yunnan Rubber Plantation. in Proceedings of the fourth national agricultural environmental science symposium 367–375 (2011).
A286: 285 | B286: Quincke, J. A. et al. One-time tillage of no-till systems: Soil physical properties, phosphorus runoff, and crop yield. Agron. J. 99, 1104–1110 (2007). | C286: 285 | D286: Sun, J., Liu, M., Li, L., Liu, J. & Sayre., K. D. Effects of tillage mode on soil erosion on rain-fed cropland in Inner Mongolia. Chinese J. Ecol. 29, 485–490 (2010).
A287: 286 | B287: R. S. Kanwar, J. L. Baker & D. G. Baker. Tillage and split N-fertilization effects on subsurface drainage water quality and crop yields. Trans. ASAE 31, 453–461 (1988). | C287: 286 | D287: Fu, Q., Luo, Y. & Chai, X. Ecological Effects and Economic Bencfit of the Complex Agro-Forestry Systems in Low-Hilland Red Soil Areas. Chinese J. Ecol. 14, 11–15 (1995).
A288: 287 | B288: Radford, B. J. & Thornton, C. M. Effects of 27 years of reduced tillage practices on soil properties and crop performance in the semi-arid subtropics of Australia. Int. J. Energy Environ. Econ. 19, 565 (2011). | C288: 287 | D288: Xu, P. Experimental study on soil erosion prevention and cure with conservation tillage in Jilin region. (Northeast Normal University, 2006).
A289: 288 | B289: Ram, H., Kler, D. S., Singh, Y. & Kumar, K. Productivity of maize (Zea mays) - wheat (Triticum aestivum) system under different tillage and crop establishment practices. Indian J. Agron. 55, 185–190 (2010). | C289: 288 | D289: USDA-ARS. USDA agriculture handbooks. (1979).
A290: 289 | B290: Ram, H., Kumar, K., Kler, D. S. & Singh, Y. Effect of permanent bed planting and tillage options on microenvironment, crop productivity, water use efficiency, and soil properties under soybean (Glycine max L.) - wheat (Triticum aestivum L.) cropping system. Ecol. Environ. Conserv. 16, 593–599 (2010). | C290: 289 | D290: Leys, J. F. & Heinjus, D. Simulated wind erosion in the South Australian Murray Mallee. (Conservation Service of NSW, 1991).
A291: 290 | B291: Ramos, M. C., Pareja‐Sánchez, E., Plaza‐Bonilla, D., Cantero‐Martínez, C. & Lampurlanés, J. Soil sealing and soil water content under no‐tillage and conventional tillage in irrigated corn: Effects on grain yield. Hydrol. Process. 33, 2095–2109 (2019). | C291: 290 | D291: Zhao, J. F., Huang, G. B., Xin, P., Xie, K. Z. & Xu, A. X. Runoff and quantity of soil erosion under conservation tillage system by simulated rainfall. Bull. Soil Water Conserv. 27, 16–19 (2007).
A292: 291 | B292: Rao, S. C. & Dao, T. H. Nitrogen placement and tillage effects on dry matter and nitrogen accumulation and redistribution in winter wheat. Agron. J. 88, 365–371 (1996). | C292: 291 | D292: Tan, C. Effects of conservation tillage on the soil nutrients maintenance and control of water erosion of sloping farmland. (Northwest A&F University, 2015).
A293: 292 | B293: Rashid, M. H., Timsina, J., Islam, N. & Islam, S. Tillage and residue-management effects on productivity, profitability and soil properties in a rice-maize-mungbean system in the Eastern Gangetic Plains. J. Crop Improv. 33, 683–710 (2019). | C293: 292 | D293: ZHAO, X., WANG, H., LI, L. & CUI, T. Impact of conservation tillage on crop growth and soil and water retaining under grain-legume-grass strip intercropping in slope land. Agric. Res. Arid Areas 31, 7–30 (2013).
A294: 293 | B294: Rasmussen, P. E. & Douglas, C. L. The influence of tillage and cropping-intensity on cereal response to nitrogen, sulfur, and phosphorus. Fertil. Res. 31, 15–19 (1992). | C294: 293 | D294: Zhang, Y., Xu, X., Sui, Y. & Lu, G. The research of the influence of conservation tillage on the soil conservation in sloping black soil zone. Jilin Water Resour. 11, 1–5 (2012).
... A322: 321 | B322: Sharratt, B. . Barley yield and evapotranspiration governed by tillage practices in interior Alaska. Soil Tillage Res. 46, 225–229 (1998). | C322: 321 | D322: Banda, A. Z., J. A. Maghembe, D. N. Ngugi, and V. A. Chome. Effect of intercropping maize and closely spacedLeucaena hedgerows on soil conservation and maize yield on a steep slope at Ntcheu, Malawi. Agroforestry systems 27, no. 1, 17-22 (1994).
A323: 322 | B323: Si, P. et al. Effect of no-tillage with straw mulch and conventional tillage on soil organic carbon pools in Northern China. Arch. Agron. Soil Sci. 64, 398–408 (2018).
A324: 323 | B324: Sidhu, D. & Duiker, S. W. Soil compaction in conservation tillage: crop impacts. Agron. J. 98, 1257–1264 (2006).
A325: 324 | B325: Silva, F. A. M., Naudin, K., Corbeels, M., Scopel, E. & Affholder, F. Impact of conservation agriculture on the agronomic and environmental performances of maize cropping under contrasting climatic conditions of the Brazilian Cerrado. F. Crop. Res. 230, 72–83 (2019).
A326: 325 | B326: Silva, P., Garrido, M., Shertzer, G. & Acevedo, E. Amount of Rain Until Third Leaf Explain Differences in Irrigated Durum Wheat Yield Between a Conventional and No-Tillage System in a Long-Term Crop Rotation System in Mediterranean Environment. Int. J. Plant Prod. 13, 339–346 (2019).
A327: 326 | B327: Simón, M. R. et al. Integrated foliar disease management to prevent yield loss in Argentinian wheat production. Agron. J. 103, 1441–1451 (2011).
A328: 327 | B328: Singer, J. W. et al. Tillage and compost affect yield of corn, soybean, and wheat and soil fertility. Agron. J. 96, 531–537 (2004).
A329: 328 | B329: Singer, J. W., Logsdon, S. D. & Meek, D. W. Tillage and compost effects on corn growth, nutrient accumulation, and grain yield. Agron. J. 99, 80–87 (2007).
A330: 329 | B330: Singer, J. W., Logsdon, S. D. & Meek, D. W. Soybean growth and seed yield response to tillage and compost. Agron. J. 100, 1039–1046 (2008).
A331: 330 | B331: Singh, V., Ram, S., Bhatnagar, A. & Savita, U. Effect of tillage methods on soil properties and productivity of quality protein maize (Zea mays)-wheat (Triticum aestivum) system. Indian J. Agron. 56, 83–87 (2011).
A332: 331 | B332: Singh, V. K. et al. Soil physical properties, yield trends and economics after five years of conservation agriculture based rice-maize system in north-western India. Soil Tillage Res. 155, 133–148 (2016).
A333: 332 | B333: Sistani, K. R., Sikora, F. J. & Rasnake, M. Poultry litter and tillage influences on corn production and soil nutrients in a Kentucky silt loam soil. Soil Tillage Res. 98, 130–139 (2008).
A334: 333 | B334: Sistani, K. R. et al. Nutrient source and tillage impact on corn grain yield and soil properties. Soil Sci. 175, 593–600 (2010).
... A414: 413 | B414: Žugec, I. The effect of reduced soil tillage on maize (Zea mays L.) grain yield in Eastern Crotia (Yugoslavia). Soil Tillage Res. 7, 19–28 (1986).
